[{"url":"https://so.toutiao.com/search?keyword=娶智障新娘男子：不是网上传的那样","word":"娶智障新娘男子：不是网上传的那样"},{"url":"https://so.toutiao.com/search?keyword=少年扶老人被讹5千元+老人女儿发声","word":"少年扶老人被讹5千元 老人女儿发声"},{"url":"https://so.toutiao.com/search?keyword=北斗是守护国家的金钥匙","word":"北斗是守护国家的金钥匙"},{"url":"https://so.toutiao.com/search?keyword=田启文辟谣吴孟达遗体运回厦门","word":"田启文辟谣吴孟达遗体运回厦门"},{"url":"https://so.toutiao.com/search?keyword=全职妈妈离婚后会一无所有吗","word":"全职妈妈离婚后会一无所有吗"},{"url":"https://so.toutiao.com/search?keyword=中国登钓鱼岛日本将动武？中方回应","word":"中国登钓鱼岛日本将动武？中方回应"},{"url":"https://so.toutiao.com/search?keyword=微博之夜尴尬瞬间","word":"微博之夜尴尬瞬间"},{"url":"https://so.toutiao.com/search?keyword=台军方下令多买凤梨挺农民","word":"台军方下令多买凤梨挺农民"},{"url":"https://so.toutiao.com/search?keyword=老外怒赞中国脱贫：简直是人类奇迹","word":"老外怒赞中国脱贫：简直是人类奇迹"},{"url":"https://so.toutiao.com/search?keyword=菠萝禁令是政治打压？国台办批驳","word":"菠萝禁令是政治打压？国台办批驳"},{"url":"https://so.toutiao.com/search?keyword=官方通报五旬男子娶智障女：无法领证","word":"官方通报五旬男子娶智障女：无法领证"},{"url":"https://so.toutiao.com/search?keyword=帮失散20年双胞胎重聚志愿者抖音发声","word":"帮失散20年双胞胎重聚志愿者抖音发声"},{"url":"https://so.toutiao.com/search?keyword=宋丹丹祝贺继女赵婷获金球奖","word":"宋丹丹祝贺继女赵婷获金球奖"},{"url":"https://so.toutiao.com/search?keyword=河南1152公斤炸药爆破拆除小产权房","word":"河南1152公斤炸药爆破拆除小产权房"},{"url":"https://so.toutiao.com/search?keyword=华人女导演赵婷揽获两项金球奖大奖","word":"华人女导演赵婷揽获两项金球奖大奖"},{"url":"https://so.toutiao.com/search?keyword=法国舰艇闯南海+国防部回应","word":"法国舰艇闯南海 国防部回应"},{"url":"https://so.toutiao.com/search?keyword=陕西面条你一次能吃几根？","word":"陕西面条你一次能吃几根？"},{"url":"https://so.toutiao.com/search?keyword=晚点对话华为鸿蒙掌舵人王成录","word":"晚点对话华为鸿蒙掌舵人王成录"},{"url":"https://so.toutiao.com/search?keyword=解放军军机连续两天进入台西南空域","word":"解放军军机连续两天进入台西南空域"},{"url":"https://so.toutiao.com/search?keyword=女子捡26万现金+失主“拒绝”认领","word":"女子捡26万现金 失主“拒绝”认领"},{"url":"https://so.toutiao.com/search?keyword=昂山素季或面临新指控","word":"昂山素季或面临新指控"},{"url":"https://so.toutiao.com/search?keyword=女护士在副院长家楼顶死亡案新进展","word":"女护士在副院长家楼顶死亡案新进展"},{"url":"https://so.toutiao.com/search?keyword=大学生缺钱冒充警察罚款","word":"大学生缺钱冒充警察罚款"},{"url":"https://so.toutiao.com/search?keyword=莫迪呼吁印民众做好准备迎接雨季","word":"莫迪呼吁印民众做好准备迎接雨季"},{"url":"https://so.toutiao.com/search?keyword=人工增雨弹误落村民家中","word":"人工增雨弹误落村民家中"},{"url":"https://so.toutiao.com/search?keyword=白鹿原景区致歉“面条15元四根”","word":"白鹿原景区致歉“面条15元四根”"},{"url":"https://so.toutiao.com/search?keyword=一周台海观察：解放军巡台低空飞行","word":"一周台海观察：解放军巡台低空飞行"},{"url":"https://so.toutiao.com/search?keyword=男子捡女同事手机后索要两千","word":"男子捡女同事手机后索要两千"},{"url":"https://so.toutiao.com/search?keyword=江西直升机坠毁砸中民房","word":"江西直升机坠毁砸中民房"},{"url":"https://so.toutiao.com/search?keyword=台湾凤梨将改销东南亚？媒体解读","word":"台湾凤梨将改销东南亚？媒体解读"},{"url":"https://so.toutiao.com/search?keyword=男子强奸未遂被打后报警被刑拘","word":"男子强奸未遂被打后报警被刑拘"},{"url":"https://so.toutiao.com/search?keyword=章子怡恭喜赵婷获金球奖","word":"章子怡恭喜赵婷获金球奖"},{"url":"https://so.toutiao.com/search?keyword=辣笔小球忏悔：我良知泯灭","word":"辣笔小球忏悔：我良知泯灭"},{"url":"https://so.toutiao.com/search?keyword=张萌穿束腰裙","word":"张萌穿束腰裙"},{"url":"https://so.toutiao.com/search?keyword=男老师为学生们系蝴蝶结打包新课本","word":"男老师为学生们系蝴蝶结打包新课本"},{"url":"https://so.toutiao.com/search?keyword=​C919客机全球首单正式落地","word":"​C919客机全球首单正式落地"},{"url":"https://so.toutiao.com/search?keyword=美要求释放47名乱港分子+中方驳斥","word":"美要求释放47名乱港分子 中方驳斥"},{"url":"https://so.toutiao.com/search?keyword=男子患白血病前妻一家悉心照顾","word":"男子患白血病前妻一家悉心照顾"},{"url":"https://so.toutiao.com/search?keyword=金球奖完整获奖名单出炉","word":"金球奖完整获奖名单出炉"},{"url":"https://so.toutiao.com/search?keyword=小沈阳一家三口走机场","word":"小沈阳一家三口走机场"},{"url":"https://so.toutiao.com/search?keyword=小孩因不让坐太近看电视摔砸东西","word":"小孩因不让坐太近看电视摔砸东西"},{"url":"https://so.toutiao.com/search?keyword=2020年个税年度汇算清缴来了","word":"2020年个税年度汇算清缴来了"},{"url":"https://so.toutiao.com/search?keyword=空巢老人一辈子未婚独居深山","word":"空巢老人一辈子未婚独居深山"},{"url":"https://so.toutiao.com/search?keyword=延迟退休如何小步走稳","word":"延迟退休如何小步走稳"},{"url":"https://so.toutiao.com/search?keyword=CBA第三阶段开启：上海力克山东","word":"CBA第三阶段开启：上海力克山东"},{"url":"https://so.toutiao.com/search?keyword=男子求婚未开口女子秒答应","word":"男子求婚未开口女子秒答应"},{"url":"https://so.toutiao.com/search?keyword=张近东如何一步步失去苏宁控制权","word":"张近东如何一步步失去苏宁控制权"},{"url":"https://so.toutiao.com/search?keyword=越南在南海岛礁建海空防御系统","word":"越南在南海岛礁建海空防御系统"},{"url":"https://so.toutiao.com/search?keyword=蔡少芬太拼命深夜就诊后立刻返工","word":"蔡少芬太拼命深夜就诊后立刻返工"},{"url":"https://so.toutiao.com/search?keyword=华晨宇邓紫棋同台领奖","word":"华晨宇邓紫棋同台领奖"},{"url":"https://so.toutiao.com/search?keyword=叙利亚称以色列空袭大马士革周边","word":"叙利亚称以色列空袭大马士革周边"},{"url":"https://so.toutiao.com/search?keyword=驻马店残疾女孩嫁老大爷+官方回应","word":"驻马店残疾女孩嫁老大爷 官方回应"},{"url":"https://so.toutiao.com/search?keyword=台军伙食怎么样？可能三餐皆凤梨","word":"台军伙食怎么样？可能三餐皆凤梨"},{"url":"https://so.toutiao.com/search?keyword=二十年后男子认出网络寻亲同胞弟弟","word":"二十年后男子认出网络寻亲同胞弟弟"},{"url":"https://so.toutiao.com/search?keyword=宋丹丹祝贺“女儿”赵婷获金球奖","word":"宋丹丹祝贺“女儿”赵婷获金球奖"},{"url":"https://so.toutiao.com/search?keyword=李子柒造型直播幻灭","word":"李子柒造型直播幻灭"},{"url":"https://so.toutiao.com/search?keyword=知名荐股机构被查+147人被抓","word":"知名荐股机构被查 147人被抓"},{"url":"https://so.toutiao.com/search?keyword=郭晶晶一家五口同框","word":"郭晶晶一家五口同框"},{"url":"https://so.toutiao.com/search?keyword=《心灵奇旅》摘金球奖最佳动画","word":"《心灵奇旅》摘金球奖最佳动画"},{"url":"https://so.toutiao.com/search?keyword=曾志伟评价吴孟达","word":"曾志伟评价吴孟达"},{"url":"https://so.toutiao.com/search?keyword=包贝尔+表演是我赖以生存的职业","word":"包贝尔 表演是我赖以生存的职业"},{"url":"https://so.toutiao.com/search?keyword=曾光教授一出场我就哭了","word":"曾光教授一出场我就哭了"},{"url":"https://so.toutiao.com/search?keyword=福原爱喊话跟拍记者：直接来问我","word":"福原爱喊话跟拍记者：直接来问我"},{"url":"https://so.toutiao.com/search?keyword=特朗普暗示或参加2024总统大选","word":"特朗普暗示或参加2024总统大选"},{"url":"https://so.toutiao.com/search?keyword=中国黑客攻击印度电网？中方辟谣","word":"中国黑客攻击印度电网？中方辟谣"},{"url":"https://so.toutiao.com/search?keyword=广厦男篮惨负青岛六连胜终结","word":"广厦男篮惨负青岛六连胜终结"},{"url":"https://so.toutiao.com/search?keyword=贾玲杨紫错位图","word":"贾玲杨紫错位图"},{"url":"https://so.toutiao.com/search?keyword=抖音电商发布消费者权益保护年报","word":"抖音电商发布消费者权益保护年报"},{"url":"https://so.toutiao.com/search?keyword=如何看待高空抛物罪今日起施行","word":"如何看待高空抛物罪今日起施行"},{"url":"https://so.toutiao.com/search?keyword=王一博日记","word":"王一博日记"},{"url":"https://so.toutiao.com/search?keyword=干饭人金晨","word":"干饭人金晨"},{"url":"https://so.toutiao.com/search?keyword=中芯国际获得美供应商供应许可","word":"中芯国际获得美供应商供应许可"},{"url":"https://so.toutiao.com/search?keyword=足协：对苏宁停止运营表示遗憾","word":"足协：对苏宁停止运营表示遗憾"},{"url":"https://so.toutiao.com/search?keyword=TVB举行吴孟达悼念活动","word":"TVB举行吴孟达悼念活动"},{"url":"https://so.toutiao.com/search?keyword=驻马店残疾女孩嫁给老大爷","word":"驻马店残疾女孩嫁给老大爷"},{"url":"https://so.toutiao.com/search?keyword=为照顾“女友”生意贷款30万做按摩","word":"为照顾“女友”生意贷款30万做按摩"},{"url":"https://so.toutiao.com/search?keyword=女子一口气买29万的私教课","word":"女子一口气买29万的私教课"},{"url":"https://so.toutiao.com/search?keyword=诋毁戍边英雄网民辣笔小球被批捕","word":"诋毁戍边英雄网民辣笔小球被批捕"},{"url":"https://so.toutiao.com/search?keyword=火箭11连败","word":"火箭11连败"},{"url":"https://so.toutiao.com/search?keyword=老人医院痛哭求助记者想见子女","word":"老人医院痛哭求助记者想见子女"},{"url":"https://so.toutiao.com/search?keyword=女嘉宾被印小天吓到捂眼","word":"女嘉宾被印小天吓到捂眼"},{"url":"https://so.toutiao.com/search?keyword=武汉弘芯疑遣散全体员工","word":"武汉弘芯疑遣散全体员工"},{"url":"https://so.toutiao.com/search?keyword=90元一斤+你实现香椿自由了吗","word":"90元一斤 你实现香椿自由了吗"},{"url":"https://so.toutiao.com/search?keyword=苏宁易购复牌涨停","word":"苏宁易购复牌涨停"},{"url":"https://so.toutiao.com/search?keyword=黄蜂逆转胜国王","word":"黄蜂逆转胜国王"},{"url":"https://so.toutiao.com/search?keyword=为省婚车钱新郎抱新娘回家","word":"为省婚车钱新郎抱新娘回家"},{"url":"https://so.toutiao.com/search?keyword=台湾军事力量能抵抗大陆？专家回应","word":"台湾军事力量能抵抗大陆？专家回应"},{"url":"https://so.toutiao.com/search?keyword=钓友因不让钓鱼用鱼竿放风筝","word":"钓友因不让钓鱼用鱼竿放风筝"},{"url":"https://so.toutiao.com/search?keyword=广东一男子乘车误点强闯闸机被罚","word":"广东一男子乘车误点强闯闸机被罚"},{"url":"https://so.toutiao.com/search?keyword=特朗普演讲突然被中断","word":"特朗普演讲突然被中断"},{"url":"https://so.toutiao.com/search?keyword=奥拉迪波拒绝火箭2年续约合同","word":"奥拉迪波拒绝火箭2年续约合同"},{"url":"https://so.toutiao.com/search?keyword=吴孟达遗产分配方案","word":"吴孟达遗产分配方案"},{"url":"https://so.toutiao.com/search?keyword=女子举报交警丈夫为工作遗弃第三孩","word":"女子举报交警丈夫为工作遗弃第三孩"},{"url":"https://so.toutiao.com/search?keyword=赵本山儿子模仿赵本山太像了","word":"赵本山儿子模仿赵本山太像了"},{"url":"https://so.toutiao.com/search?keyword=新冠康复者被挡小区外：怕延长隔离","word":"新冠康复者被挡小区外：怕延长隔离"},{"url":"https://so.toutiao.com/search?keyword=詹姆斯19分湖人胜勇士","word":"詹姆斯19分湖人胜勇士"},{"url":"https://so.toutiao.com/search?keyword=张含韵超紧身黑色燕尾裙","word":"张含韵超紧身黑色燕尾裙"},{"url":"https://so.toutiao.com/search?keyword=联合国：缅军方用致命武力致18死","word":"联合国：缅军方用致命武力致18死"},{"url":"https://so.toutiao.com/search?keyword=东体：天津未来将组建一支中冠队","word":"东体：天津未来将组建一支中冠队"},{"url":"https://so.toutiao.com/search?keyword=女子称被男性朋友强奸未遂殴打住院","word":"女子称被男性朋友强奸未遂殴打住院"},{"url":"https://so.toutiao.com/search?keyword=2021年金球奖","word":"2021年金球奖"},{"url":"https://so.toutiao.com/search?keyword=周星驰的黄金配角们现状如何","word":"周星驰的黄金配角们现状如何"},{"url":"https://so.toutiao.com/search?keyword=央视时隔14年再次播放日本动画","word":"央视时隔14年再次播放日本动画"},{"url":"https://so.toutiao.com/search?keyword=被李佳琦金靖笑死","word":"被李佳琦金靖笑死"},{"url":"https://so.toutiao.com/search?keyword=女生查到考研成绩又哭又笑:数学80分","word":"女生查到考研成绩又哭又笑:数学80分"},{"url":"https://so.toutiao.com/search?keyword=手机芯片全面紧缺","word":"手机芯片全面紧缺"},{"url":"https://so.toutiao.com/search?keyword=中美防务部门如何接触+国防部回应","word":"中美防务部门如何接触 国防部回应"},{"url":"https://so.toutiao.com/search?keyword=昂山素季领导政党要建临时政府","word":"昂山素季领导政党要建临时政府"},{"url":"https://so.toutiao.com/search?keyword=马丽表白小自己10岁的老公","word":"马丽表白小自己10岁的老公"},{"url":"https://so.toutiao.com/search?keyword=曝华为新芯片已流片","word":"曝华为新芯片已流片"},{"url":"https://so.toutiao.com/search?keyword=太阳送森林狼8连败","word":"太阳送森林狼8连败"},{"url":"https://so.toutiao.com/search?keyword=赵婷创造金球奖历史","word":"赵婷创造金球奖历史"},{"url":"https://so.toutiao.com/search?keyword=江疏影没浪费贴纸","word":"江疏影没浪费贴纸"},{"url":"https://so.toutiao.com/search?keyword=茅台学院首届本科生今年毕业","word":"茅台学院首届本科生今年毕业"},{"url":"https://so.toutiao.com/search?keyword=老人买银行理财亏18万获赔","word":"老人买银行理财亏18万获赔"},{"url":"https://so.toutiao.com/search?keyword=东体：特谢拉曾因欠薪爆粗口","word":"东体：特谢拉曾因欠薪爆粗口"},{"url":"https://so.toutiao.com/search?keyword=塔图姆准绝杀+凯尔特人胜奇才","word":"塔图姆准绝杀 凯尔特人胜奇才"},{"url":"https://so.toutiao.com/search?keyword=全国政协会议议程来了","word":"全国政协会议议程来了"},{"url":"https://so.toutiao.com/search?keyword=美空军将领催促尽快研发部署6代机","word":"美空军将领催促尽快研发部署6代机"},{"url":"https://so.toutiao.com/search?keyword=董明珠+成功不是拥有亿万财富","word":"董明珠 成功不是拥有亿万财富"},{"url":"https://so.toutiao.com/search?keyword=总局同意中超4月20日开赛方案","word":"总局同意中超4月20日开赛方案"},{"url":"https://so.toutiao.com/search?keyword=雄鹿赢快船获五连胜","word":"雄鹿赢快船获五连胜"},{"url":"https://so.toutiao.com/search?keyword=深圳国资拟收购苏宁23%股份","word":"深圳国资拟收购苏宁23%股份"},{"url":"https://so.toutiao.com/search?keyword=baby活动上与黄晓明坐对面却无交流","word":"baby活动上与黄晓明坐对面却无交流"},{"url":"https://so.toutiao.com/search?keyword=80艘越南渔船上月侵入中国部分水域","word":"80艘越南渔船上月侵入中国部分水域"},{"url":"https://so.toutiao.com/search?keyword=希金斯时隔三年再夺冠","word":"希金斯时隔三年再夺冠"},{"url":"https://so.toutiao.com/search?keyword=47名乱港分子涉嫌颠覆国家政权被诉","word":"47名乱港分子涉嫌颠覆国家政权被诉"},{"url":"https://so.toutiao.com/search?keyword=肖战贾玲拥抱","word":"肖战贾玲拥抱"},{"url":"https://so.toutiao.com/search?keyword=小沈阳发文告别《我就是演员》","word":"小沈阳发文告别《我就是演员》"},{"url":"https://so.toutiao.com/search?keyword=热刺4-0伯恩利结束连败","word":"热刺4-0伯恩利结束连败"},{"url":"https://so.toutiao.com/search?keyword=3位上将履新全国人大","word":"3位上将履新全国人大"},{"url":"https://so.toutiao.com/search?keyword=一家四口开车出游遭天降轮胎砸中","word":"一家四口开车出游遭天降轮胎砸中"},{"url":"https://so.toutiao.com/search?keyword=切尔西0-0闷平曼联","word":"切尔西0-0闷平曼联"},{"url":"https://so.toutiao.com/search?keyword=90元一斤+你实现“香椿自由”了吗","word":"90元一斤 你实现“香椿自由”了吗"},{"url":"https://so.toutiao.com/search?keyword=实名举报中国人寿当事人再发声","word":"实名举报中国人寿当事人再发声"},{"url":"https://so.toutiao.com/search?keyword=武磊登场+西班牙人客平希洪竞技","word":"武磊登场 西班牙人客平希洪竞技"},{"url":"https://so.toutiao.com/search?keyword=发展联盟：林书豪25分率队取胜","word":"发展联盟：林书豪25分率队取胜"},{"url":"https://so.toutiao.com/search?keyword=台媒：大陆贸易商叫停高雄莲雾订单","word":"台媒：大陆贸易商叫停高雄莲雾订单"},{"url":"https://so.toutiao.com/search?keyword=张小斐让大家多给妈长点脸","word":"张小斐让大家多给妈长点脸"},{"url":"https://so.toutiao.com/search?keyword=河北队官宣两球员加盟","word":"河北队官宣两球员加盟"},{"url":"https://so.toutiao.com/search?keyword=一针药70万+夫妻刷11张银行卡救娃","word":"一针药70万 夫妻刷11张银行卡救娃"},{"url":"https://so.toutiao.com/search?keyword=《海外行动》大结局","word":"《海外行动》大结局"},{"url":"https://so.toutiao.com/search?keyword=微信“戒烟”背后","word":"微信“戒烟”背后"},{"url":"https://so.toutiao.com/search?keyword=李国英任水利部部长","word":"李国英任水利部部长"},{"url":"https://so.toutiao.com/search?keyword=王一博开年演讲","word":"王一博开年演讲"},{"url":"https://so.toutiao.com/search?keyword=复旦教授：延迟退休应拉平年龄","word":"复旦教授：延迟退休应拉平年龄"},{"url":"https://so.toutiao.com/search?keyword=台“海巡署”本月将举行2次演训","word":"台“海巡署”本月将举行2次演训"},{"url":"https://so.toutiao.com/search?keyword=一口气买29万私教课","word":"一口气买29万私教课"},{"url":"https://so.toutiao.com/search?keyword=邯郸城管车辆无牌上路","word":"邯郸城管车辆无牌上路"},{"url":"https://so.toutiao.com/search?keyword=教师被明确禁止的7类行为","word":"教师被明确禁止的7类行为"},{"url":"https://so.toutiao.com/search?keyword=美方涉钓鱼岛主权表态无常闹哪出","word":"美方涉钓鱼岛主权表态无常闹哪出"},{"url":"https://so.toutiao.com/search?keyword=中超冠军江苏苏宁停止运营","word":"中超冠军江苏苏宁停止运营"},{"url":"https://so.toutiao.com/search?keyword=国米3-0热那亚","word":"国米3-0热那亚"},{"url":"https://so.toutiao.com/search?keyword=中国成泰国榴莲全球最大买家","word":"中国成泰国榴莲全球最大买家"},{"url":"https://so.toutiao.com/search?keyword=利物浦2-0胜谢菲联+终结四连败","word":"利物浦2-0胜谢菲联 终结四连败"},{"url":"https://so.toutiao.com/search?keyword=香椿90元一斤+为何这么“香”","word":"香椿90元一斤 为何这么“香”"},{"url":"https://so.toutiao.com/search?keyword=美保守派讨论6大涉中国议题","word":"美保守派讨论6大涉中国议题"},{"url":"https://so.toutiao.com/search?keyword=吴孟达财产分配方案","word":"吴孟达财产分配方案"},{"url":"https://so.toutiao.com/search?keyword=美连射洲际导弹+核战争有赢家吗","word":"美连射洲际导弹 核战争有赢家吗"},{"url":"https://so.toutiao.com/search?keyword=解放军军机再度巡航台湾","word":"解放军军机再度巡航台湾"},{"url":"https://so.toutiao.com/search?keyword=利物浦终结四连败","word":"利物浦终结四连败"},{"url":"https://so.toutiao.com/search?keyword=男子炸伤叔叔火烧村支书家","word":"男子炸伤叔叔火烧村支书家"},{"url":"https://so.toutiao.com/search?keyword=陈思诚秦昊换座","word":"陈思诚秦昊换座"},{"url":"https://so.toutiao.com/search?keyword=董明珠：在格力干到退休给你房","word":"董明珠：在格力干到退休给你房"},{"url":"https://so.toutiao.com/search?keyword=一南一北两位省委书记多了新身份","word":"一南一北两位省委书记多了新身份"},{"url":"https://so.toutiao.com/search?keyword=热刺胜伯恩利","word":"热刺胜伯恩利"},{"url":"https://so.toutiao.com/search?keyword=田启文：吴孟达家人分遗产是谣传","word":"田启文：吴孟达家人分遗产是谣传"},{"url":"https://so.toutiao.com/search?keyword=秦昊问自己20年+我还有机会吗","word":"秦昊问自己20年 我还有机会吗"},{"url":"https://so.toutiao.com/search?keyword=董明珠谈对接班人的要求","word":"董明珠谈对接班人的要求"},{"url":"https://so.toutiao.com/search?keyword=水库擅自开闸+下游集市摊位被冲","word":"水库擅自开闸 下游集市摊位被冲"},{"url":"https://so.toutiao.com/search?keyword=老人见孙子被训哭拿面杖打儿子","word":"老人见孙子被训哭拿面杖打儿子"},{"url":"https://so.toutiao.com/search?keyword=台湾教授谈“菠萝禁令”","word":"台湾教授谈“菠萝禁令”"},{"url":"https://so.toutiao.com/search?keyword=奥卡姆剃刀评“华为跨界养猪”","word":"奥卡姆剃刀评“华为跨界养猪”"},{"url":"https://so.toutiao.com/search?keyword=苏宁将在深圳设立华南地区总部","word":"苏宁将在深圳设立华南地区总部"},{"url":"https://so.toutiao.com/search?keyword=2020人均GDP为72447元","word":"2020人均GDP为72447元"},{"url":"https://so.toutiao.com/search?keyword=日本威胁中国登上钓鱼岛或开火","word":"日本威胁中国登上钓鱼岛或开火"},{"url":"https://so.toutiao.com/search?keyword=明星争相与丁真合影","word":"明星争相与丁真合影"},{"url":"https://so.toutiao.com/search?keyword=吴孟达临终前曾用力睁眼看亲人","word":"吴孟达临终前曾用力睁眼看亲人"},{"url":"https://so.toutiao.com/search?keyword=邓亚萍+电竞和传统体育都是竞技体育","word":"邓亚萍 电竞和传统体育都是竞技体育"},{"url":"https://so.toutiao.com/search?keyword=人民日报：爱国者达叔永远是主角","word":"人民日报：爱国者达叔永远是主角"},{"url":"https://so.toutiao.com/search?keyword=台湾果农发声怒斥民进党","word":"台湾果农发声怒斥民进党"},{"url":"https://so.toutiao.com/search?keyword=山西省发现千亿方大气田","word":"山西省发现千亿方大气田"},{"url":"https://so.toutiao.com/search?keyword=港片黄金时代回不去了","word":"港片黄金时代回不去了"},{"url":"https://so.toutiao.com/search?keyword=民进党元老：台湾靠大陆奶水养大","word":"民进党元老：台湾靠大陆奶水养大"},{"url":"https://so.toutiao.com/search?keyword=比亚迪成为巴菲特唯一重仓中国公司","word":"比亚迪成为巴菲特唯一重仓中国公司"},{"url":"https://so.toutiao.com/search?keyword=章子怡请大家记住潘斌龙这个名字","word":"章子怡请大家记住潘斌龙这个名字"},{"url":"https://so.toutiao.com/search?keyword=男孩脚踹幼儿挑衅大人：我是你爹","word":"男孩脚踹幼儿挑衅大人：我是你爹"},{"url":"https://so.toutiao.com/search?keyword=美国堪萨斯州发生爆炸","word":"美国堪萨斯州发生爆炸"},{"url":"https://so.toutiao.com/search?keyword=大连华讯12名高管被深圳警方逮捕","word":"大连华讯12名高管被深圳警方逮捕"},{"url":"https://so.toutiao.com/search?keyword=茅台集团去年营收超1140亿元","word":"茅台集团去年营收超1140亿元"},{"url":"https://so.toutiao.com/search?keyword=江苏小学实施课后服务","word":"江苏小学实施课后服务"},{"url":"https://so.toutiao.com/search?keyword=河南男孩扶倒地老人被“讹”5000","word":"河南男孩扶倒地老人被“讹”5000"},{"url":"https://so.toutiao.com/search?keyword=媒体：吴孟达遗体将搭乘专机回福建","word":"媒体：吴孟达遗体将搭乘专机回福建"},{"url":"https://so.toutiao.com/search?keyword=苏宁易购：股票于3月1日复牌","word":"苏宁易购：股票于3月1日复牌"},{"url":"https://so.toutiao.com/search?keyword=霍汶希杜华组合名叫霍建华","word":"霍汶希杜华组合名叫霍建华"},{"url":"https://so.toutiao.com/search?keyword=全国首例双肺肝脏同期联合移植","word":"全国首例双肺肝脏同期联合移植"},{"url":"https://so.toutiao.com/search?keyword=淄博蹴鞠压哨交表+将参加中甲","word":"淄博蹴鞠压哨交表 将参加中甲"},{"url":"https://so.toutiao.com/search?keyword=57岁毛阿敏近照曝光","word":"57岁毛阿敏近照曝光"},{"url":"https://so.toutiao.com/search?keyword=马来西亚前总理纳吉布悼念吴孟达","word":"马来西亚前总理纳吉布悼念吴孟达"},{"url":"https://so.toutiao.com/search?keyword=男子拖1吨硬币存钱+银行清点3天","word":"男子拖1吨硬币存钱 银行清点3天"},{"url":"https://so.toutiao.com/search?keyword=拜登：美国空袭叙利亚是自卫","word":"拜登：美国空袭叙利亚是自卫"},{"url":"https://so.toutiao.com/search?keyword=《李焕英》总票房超《流浪地球》","word":"《李焕英》总票房超《流浪地球》"},{"url":"https://so.toutiao.com/search?keyword=《流浪地球》主创悼念吴孟达","word":"《流浪地球》主创悼念吴孟达"},{"url":"https://so.toutiao.com/search?keyword=SN两局横扫2-0击败iG","word":"SN两局横扫2-0击败iG"},{"url":"https://so.toutiao.com/search?keyword=男性避孕药研发重大突破","word":"男性避孕药研发重大突破"},{"url":"https://so.toutiao.com/search?keyword=美国针对沙特重提卡舒吉案有何深意","word":"美国针对沙特重提卡舒吉案有何深意"},{"url":"https://so.toutiao.com/search?keyword=欠闺蜜600万不还上门撬锁偷欠条","word":"欠闺蜜600万不还上门撬锁偷欠条"},{"url":"https://so.toutiao.com/search?keyword=买10层大蛋糕在KTV打“蛋糕战”","word":"买10层大蛋糕在KTV打“蛋糕战”"},{"url":"https://so.toutiao.com/search?keyword=鞠婧祎的腰是真实存在的吗","word":"鞠婧祎的腰是真实存在的吗"},{"url":"https://so.toutiao.com/search?keyword=爱尔眼科前员工自曝术后视力反下降","word":"爱尔眼科前员工自曝术后视力反下降"}]