[{"url":"https://so.toutiao.com/search?keyword=乌方要求俄撤出乌领土+含克里米亚","word":"乌方要求俄撤出乌领土 含克里米亚"},{"url":"https://so.toutiao.com/search?keyword=俄乌谈判现场曝光","word":"俄乌谈判现场曝光"},{"url":"https://so.toutiao.com/search?keyword=人大代表建议春节假期延长至10天","word":"人大代表建议春节假期延长至10天"},{"url":"https://so.toutiao.com/search?keyword=清华原书记陈旭任中央统战部副部长","word":"清华原书记陈旭任中央统战部副部长"},{"url":"https://so.toutiao.com/search?keyword=俄乌谈判为什么选在戈梅利","word":"俄乌谈判为什么选在戈梅利"},{"url":"https://so.toutiao.com/search?keyword=香港民政事务局局长徐英伟被免职","word":"香港民政事务局局长徐英伟被免职"},{"url":"https://so.toutiao.com/search?keyword=开战五日俄乌战争最新局势","word":"开战五日俄乌战争最新局势"},{"url":"https://so.toutiao.com/search?keyword=会否买更多能源支持俄方？中方回应","word":"会否买更多能源支持俄方？中方回应"},{"url":"https://so.toutiao.com/search?keyword=雪容融接棒上岗","word":"雪容融接棒上岗"},{"url":"https://so.toutiao.com/search?keyword=中方回应俄核威慑力量置于警戒状态","word":"中方回应俄核威慑力量置于警戒状态"},{"url":"https://so.toutiao.com/search?keyword=决战基辅+关键看美欧如何军事介入","word":"决战基辅 关键看美欧如何军事介入"},{"url":"https://so.toutiao.com/search?keyword=现场：乌代表团乘直升机到会谈地点","word":"现场：乌代表团乘直升机到会谈地点"},{"url":"https://so.toutiao.com/search?keyword=俄乌冲突中的美国：警告与应对脱节","word":"俄乌冲突中的美国：警告与应对脱节"},{"url":"https://so.toutiao.com/search?keyword=乌克兰的中国留学生为何这么多","word":"乌克兰的中国留学生为何这么多"},{"url":"https://so.toutiao.com/search?keyword=媒体人：俄乌局势出现极限对抗局面","word":"媒体人：俄乌局势出现极限对抗局面"},{"url":"https://so.toutiao.com/search?keyword=美英等国退役军人欲进入乌克兰参战","word":"美英等国退役军人欲进入乌克兰参战"},{"url":"https://so.toutiao.com/search?keyword=乌克兰要求立即加入欧盟","word":"乌克兰要求立即加入欧盟"},{"url":"https://so.toutiao.com/search?keyword=全球最大飞机安-225被毁？俄乌现分歧","word":"全球最大飞机安-225被毁？俄乌现分歧"},{"url":"https://so.toutiao.com/search?keyword=还原河南安阳“杀童案”细节","word":"还原河南安阳“杀童案”细节"},{"url":"https://so.toutiao.com/search?keyword=关于俄乌之战+哪些信息是谣言","word":"关于俄乌之战 哪些信息是谣言"},{"url":"https://so.toutiao.com/search?keyword=俄方：在乌部署核武器是美国的梦想","word":"俄方：在乌部署核武器是美国的梦想"},{"url":"https://so.toutiao.com/search?keyword=媒体：中国男性人口近60年首次减少","word":"媒体：中国男性人口近60年首次减少"},{"url":"https://so.toutiao.com/search?keyword=祖孙3人遇害：曝小女孩跑出后被追上","word":"祖孙3人遇害：曝小女孩跑出后被追上"},{"url":"https://so.toutiao.com/search?keyword=《人世间》中所表现的婚姻问题","word":"《人世间》中所表现的婚姻问题"},{"url":"https://so.toutiao.com/search?keyword=乌方：俄军已占领别尔江斯克","word":"乌方：俄军已占领别尔江斯克"},{"url":"https://so.toutiao.com/search?keyword=俄罗斯是如何打响外汇保卫战的","word":"俄罗斯是如何打响外汇保卫战的"},{"url":"https://so.toutiao.com/search?keyword=中方：中俄将继续开展正常贸易合作","word":"中方：中俄将继续开展正常贸易合作"},{"url":"https://so.toutiao.com/search?keyword=媒体：俄空军已控制整个乌克兰领空","word":"媒体：俄空军已控制整个乌克兰领空"},{"url":"https://so.toutiao.com/search?keyword=美西方祭“金融核弹”实留后门","word":"美西方祭“金融核弹”实留后门"},{"url":"https://so.toutiao.com/search?keyword=丰田将暂停所有日本工厂的生产","word":"丰田将暂停所有日本工厂的生产"},{"url":"https://so.toutiao.com/search?keyword=俄国防部：基辅市民可自由离开该市","word":"俄国防部：基辅市民可自由离开该市"},{"url":"https://so.toutiao.com/search?keyword=俄罗斯乌克兰青年一同呼吁和平","word":"俄罗斯乌克兰青年一同呼吁和平"},{"url":"https://so.toutiao.com/search?keyword=荣耀Magic4系列发布","word":"荣耀Magic4系列发布"},{"url":"https://so.toutiao.com/search?keyword=普京将于28日主持召开经济会议","word":"普京将于28日主持召开经济会议"},{"url":"https://so.toutiao.com/search?keyword=谷爱凌的明星缘有多好","word":"谷爱凌的明星缘有多好"},{"url":"https://so.toutiao.com/search?keyword=白俄罗斯公投修宪+中方：尊重支持","word":"白俄罗斯公投修宪 中方：尊重支持"},{"url":"https://so.toutiao.com/search?keyword=欧洲能离开俄罗斯吗","word":"欧洲能离开俄罗斯吗"},{"url":"https://so.toutiao.com/search?keyword=俄乌战争如何影响全球粮食格局","word":"俄乌战争如何影响全球粮食格局"},{"url":"https://so.toutiao.com/search?keyword=俄罗斯央行将基准利率提升至20%","word":"俄罗斯央行将基准利率提升至20%"},{"url":"https://so.toutiao.com/search?keyword=父亲为女儿做“冰墩墩”游戏","word":"父亲为女儿做“冰墩墩”游戏"},{"url":"https://so.toutiao.com/search?keyword=俄乌军方通报各自取得的战果","word":"俄乌军方通报各自取得的战果"},{"url":"https://so.toutiao.com/search?keyword=王毅：中方欢迎俄乌启动和平谈判","word":"王毅：中方欢迎俄乌启动和平谈判"},{"url":"https://so.toutiao.com/search?keyword=俄媒：缅甸支持俄对乌特别军事行动","word":"俄媒：缅甸支持俄对乌特别军事行动"},{"url":"https://so.toutiao.com/search?keyword=普京视察莫斯科在建航天中心","word":"普京视察莫斯科在建航天中心"},{"url":"https://so.toutiao.com/search?keyword=俄罗斯有办法绕开SWIFT系统吗","word":"俄罗斯有办法绕开SWIFT系统吗"},{"url":"https://so.toutiao.com/search?keyword=沙特境内新发现五个大型天然气田","word":"沙特境内新发现五个大型天然气田"},{"url":"https://so.toutiao.com/search?keyword=专家：欧盟武器援助无法扭转乌局势","word":"专家：欧盟武器援助无法扭转乌局势"},{"url":"https://so.toutiao.com/search?keyword=杜江霍思燕风波后同游三亚","word":"杜江霍思燕风波后同游三亚"},{"url":"https://so.toutiao.com/search?keyword=瑞士决定冻结俄罗斯在瑞士资产","word":"瑞士决定冻结俄罗斯在瑞士资产"},{"url":"https://so.toutiao.com/search?keyword=香港市民讲述两个月来疫情“质变”","word":"香港市民讲述两个月来疫情“质变”"},{"url":"https://so.toutiao.com/search?keyword=中央深改委会议：加大金融监管力度","word":"中央深改委会议：加大金融监管力度"},{"url":"https://so.toutiao.com/search?keyword=乌方：俄乌会谈核心是立即停火撤军","word":"乌方：俄乌会谈核心是立即停火撤军"},{"url":"https://so.toutiao.com/search?keyword=美欧对俄制裁或提升人民币结算需求","word":"美欧对俄制裁或提升人民币结算需求"},{"url":"https://so.toutiao.com/search?keyword=马英九谈乌克兰局势：战争无赢家","word":"马英九谈乌克兰局势：战争无赢家"},{"url":"https://so.toutiao.com/search?keyword=新一轮养老金涨幅几何","word":"新一轮养老金涨幅几何"},{"url":"https://so.toutiao.com/search?keyword=美授权驻俄使馆员工及家属自愿撤离","word":"美授权驻俄使馆员工及家属自愿撤离"},{"url":"https://so.toutiao.com/search?keyword=美称中国知情却不劝俄？中方驳斥","word":"美称中国知情却不劝俄？中方驳斥"},{"url":"https://so.toutiao.com/search?keyword=武汉长江新区正式成立","word":"武汉长江新区正式成立"},{"url":"https://so.toutiao.com/search?keyword=乌代表团成员名单公布：含国防部长","word":"乌代表团成员名单公布：含国防部长"},{"url":"https://so.toutiao.com/search?keyword=数十万乌难民涌入邻国+排队几十公里","word":"数十万乌难民涌入邻国 排队几十公里"},{"url":"https://so.toutiao.com/search?keyword=俄乌冲突或加剧乌克兰疫情蔓延","word":"俄乌冲突或加剧乌克兰疫情蔓延"},{"url":"https://so.toutiao.com/search?keyword=中使馆：柬警方查证“血奴”案属编造","word":"中使馆：柬警方查证“血奴”案属编造"},{"url":"https://so.toutiao.com/search?keyword=《人世间》胡连馨谈与宋佳吵架戏份","word":"《人世间》胡连馨谈与宋佳吵架戏份"},{"url":"https://so.toutiao.com/search?keyword=BP退出俄油或损失250亿美元","word":"BP退出俄油或损失250亿美元"},{"url":"https://so.toutiao.com/search?keyword=俄乌谈判正式开始+现场曝光","word":"俄乌谈判正式开始 现场曝光"},{"url":"https://so.toutiao.com/search?keyword=俄方：战略导弹部队等均进入战备状态","word":"俄方：战略导弹部队等均进入战备状态"},{"url":"https://so.toutiao.com/search?keyword=香港新增34466例病例+新增死亡87例","word":"香港新增34466例病例 新增死亡87例"},{"url":"https://so.toutiao.com/search?keyword=2021年度个税汇算3月1日开启","word":"2021年度个税汇算3月1日开启"},{"url":"https://so.toutiao.com/search?keyword=俄媒：美驻白俄罗斯大使馆暂停运行","word":"俄媒：美驻白俄罗斯大使馆暂停运行"},{"url":"https://so.toutiao.com/search?keyword=俄军核力量转入特殊战备意味着什么","word":"俄军核力量转入特殊战备意味着什么"},{"url":"https://so.toutiao.com/search?keyword=美国将首次向乌克兰运送防空导弹","word":"美国将首次向乌克兰运送防空导弹"},{"url":"https://so.toutiao.com/search?keyword=俄方称已掌握乌全境制空权","word":"俄方称已掌握乌全境制空权"},{"url":"https://so.toutiao.com/search?keyword=乌军袭击俄防空导弹车队画面曝光","word":"乌军袭击俄防空导弹车队画面曝光"},{"url":"https://so.toutiao.com/search?keyword=外媒：民调显示乌总统支持率飙升","word":"外媒：民调显示乌总统支持率飙升"},{"url":"https://so.toutiao.com/search?keyword=巴西总统：将在俄乌冲突中保持中立","word":"巴西总统：将在俄乌冲突中保持中立"},{"url":"https://so.toutiao.com/search?keyword=印媒：印度留学生遭乌克兰军警虐待","word":"印媒：印度留学生遭乌克兰军警虐待"},{"url":"https://so.toutiao.com/search?keyword=中企会否停止向俄发货？中方回应","word":"中企会否停止向俄发货？中方回应"},{"url":"https://so.toutiao.com/search?keyword=俄乌冲突或将进一步推高国际粮价","word":"俄乌冲突或将进一步推高国际粮价"},{"url":"https://so.toutiao.com/search?keyword=云监工香港青衣方舱医院建设","word":"云监工香港青衣方舱医院建设"},{"url":"https://so.toutiao.com/search?keyword=基辅便利店和公共交通恢复运营","word":"基辅便利店和公共交通恢复运营"},{"url":"https://so.toutiao.com/search?keyword=战火中的中国驻乌大使馆","word":"战火中的中国驻乌大使馆"},{"url":"https://so.toutiao.com/search?keyword=在乌华人哭诉朋友牺牲","word":"在乌华人哭诉朋友牺牲"},{"url":"https://so.toutiao.com/search?keyword=专家：俄核弹头装导弹+随时核打击","word":"专家：俄核弹头装导弹 随时核打击"},{"url":"https://so.toutiao.com/search?keyword=美民间号召倒掉俄国酒+有人倒错了","word":"美民间号召倒掉俄国酒 有人倒错了"},{"url":"https://so.toutiao.com/search?keyword=《新闻联播》正在直播","word":"《新闻联播》正在直播"},{"url":"https://so.toutiao.com/search?keyword=北约：将继续给乌克兰提供武器装备","word":"北约：将继续给乌克兰提供武器装备"},{"url":"https://so.toutiao.com/search?keyword=英外交大臣支持英国人去乌克兰参战","word":"英外交大臣支持英国人去乌克兰参战"},{"url":"https://so.toutiao.com/search?keyword=俄央行回应西方金融制裁","word":"俄央行回应西方金融制裁"},{"url":"https://so.toutiao.com/search?keyword=俄国防部：被俘俄军遭“纳粹般待遇”","word":"俄国防部：被俘俄军遭“纳粹般待遇”"},{"url":"https://so.toutiao.com/search?keyword=欧美企业大幅放缓融资步伐","word":"欧美企业大幅放缓融资步伐"},{"url":"https://so.toutiao.com/search?keyword=三亚前往北京航班均已取消","word":"三亚前往北京航班均已取消"},{"url":"https://so.toutiao.com/search?keyword=李晟辟谣与李佳航离婚","word":"李晟辟谣与李佳航离婚"},{"url":"https://so.toutiao.com/search?keyword=俄罗斯民众大排长龙希望提取外币","word":"俄罗斯民众大排长龙希望提取外币"},{"url":"https://so.toutiao.com/search?keyword=2021年我国出生人口1062万人","word":"2021年我国出生人口1062万人"},{"url":"https://so.toutiao.com/search?keyword=欧盟：不能完全将俄排除在SWIFT外","word":"欧盟：不能完全将俄排除在SWIFT外"},{"url":"https://so.toutiao.com/search?keyword=香港中小学暑假提前至3月7日开始","word":"香港中小学暑假提前至3月7日开始"},{"url":"https://so.toutiao.com/search?keyword=卢布重挫25%+俄罗斯央行紧急加息","word":"卢布重挫25% 俄罗斯央行紧急加息"},{"url":"https://so.toutiao.com/search?keyword=俄媒：乌克兰代表团已抵达谈判地点","word":"俄媒：乌克兰代表团已抵达谈判地点"},{"url":"https://so.toutiao.com/search?keyword=香港新增确诊病例约34466例","word":"香港新增确诊病例约34466例"},{"url":"https://so.toutiao.com/search?keyword=俄媒：参加谈判的乌代表团抵白俄","word":"俄媒：参加谈判的乌代表团抵白俄"},{"url":"https://so.toutiao.com/search?keyword=基辅留学生收到房东饺子回礼6瓶酒","word":"基辅留学生收到房东饺子回礼6瓶酒"},{"url":"https://so.toutiao.com/search?keyword=中国男性人口出现下降","word":"中国男性人口出现下降"},{"url":"https://so.toutiao.com/search?keyword=中使馆：在乌公民一个也不能少","word":"中使馆：在乌公民一个也不能少"},{"url":"https://so.toutiao.com/search?keyword=中国移动回应江西用户无信号","word":"中国移动回应江西用户无信号"},{"url":"https://so.toutiao.com/search?keyword=解放军军机今早6度进入台西南空域","word":"解放军军机今早6度进入台西南空域"},{"url":"https://so.toutiao.com/search?keyword=小鹏汽车为门店开展迷信活动道歉","word":"小鹏汽车为门店开展迷信活动道歉"},{"url":"https://so.toutiao.com/search?keyword=顿涅茨克领导人宣布已暂停总动员令","word":"顿涅茨克领导人宣布已暂停总动员令"},{"url":"https://so.toutiao.com/search?keyword=韩国中断对俄罗斯的战略物资出口","word":"韩国中断对俄罗斯的战略物资出口"},{"url":"https://so.toutiao.com/search?keyword=俄国防部：已摧毁1067个乌军事设施","word":"俄国防部：已摧毁1067个乌军事设施"},{"url":"https://so.toutiao.com/search?keyword=卢布暴跌近30%创历史新低","word":"卢布暴跌近30%创历史新低"},{"url":"https://so.toutiao.com/search?keyword=国产大飞机背后的中国黑科技","word":"国产大飞机背后的中国黑科技"},{"url":"https://so.toutiao.com/search?keyword=每个人生来都是罕见病基因携带者","word":"每个人生来都是罕见病基因携带者"},{"url":"https://so.toutiao.com/search?keyword=俄罗斯暂时禁止外国人出售证券","word":"俄罗斯暂时禁止外国人出售证券"},{"url":"https://so.toutiao.com/search?keyword=31省份新增本土确诊87例+涉9省市","word":"31省份新增本土确诊87例 涉9省市"},{"url":"https://so.toutiao.com/search?keyword=乌克兰释放大量参过军的囚犯参战","word":"乌克兰释放大量参过军的囚犯参战"},{"url":"https://so.toutiao.com/search?keyword=雪容融与冰墩墩交接道别","word":"雪容融与冰墩墩交接道别"},{"url":"https://so.toutiao.com/search?keyword=乌总统已就加入欧盟同欧委会主席通话","word":"乌总统已就加入欧盟同欧委会主席通话"},{"url":"https://so.toutiao.com/search?keyword=卫星图：大批俄军坦克向基辅推进","word":"卫星图：大批俄军坦克向基辅推进"},{"url":"https://so.toutiao.com/search?keyword=瑞士考虑冻结俄罗斯在瑞士资产","word":"瑞士考虑冻结俄罗斯在瑞士资产"},{"url":"https://so.toutiao.com/search?keyword=岸田文雄：日本不能与美共有核武器","word":"岸田文雄：日本不能与美共有核武器"},{"url":"https://so.toutiao.com/search?keyword=美驻俄使馆警告公民应考虑立即离俄","word":"美驻俄使馆警告公民应考虑立即离俄"},{"url":"https://so.toutiao.com/search?keyword=詹姆斯生涯第500场30++历史第三人","word":"詹姆斯生涯第500场30+ 历史第三人"},{"url":"https://so.toutiao.com/search?keyword=乌克兰敖德萨街区疑似布雷","word":"乌克兰敖德萨街区疑似布雷"},{"url":"https://so.toutiao.com/search?keyword=俄方称有意与乌方尽快达成共识","word":"俄方称有意与乌方尽快达成共识"},{"url":"https://so.toutiao.com/search?keyword=中国00后小将绝杀奥沙利文夺冠","word":"中国00后小将绝杀奥沙利文夺冠"},{"url":"https://so.toutiao.com/search?keyword=决战基辅+分析称乌克兰靠巷战难以支撑","word":"决战基辅 分析称乌克兰靠巷战难以支撑"},{"url":"https://so.toutiao.com/search?keyword=大宋佳近况曝光","word":"大宋佳近况曝光"},{"url":"https://so.toutiao.com/search?keyword=俄方无法保证参加日内瓦联合国会议","word":"俄方无法保证参加日内瓦联合国会议"},{"url":"https://so.toutiao.com/search?keyword=美国多州限制销售俄罗斯伏特加","word":"美国多州限制销售俄罗斯伏特加"},{"url":"https://so.toutiao.com/search?keyword=湖北武汉新增本土确诊5例","word":"湖北武汉新增本土确诊5例"},{"url":"https://so.toutiao.com/search?keyword=俄乌冲突引蓝营关注台湾命运","word":"俄乌冲突引蓝营关注台湾命运"},{"url":"https://so.toutiao.com/search?keyword=郝冬梅向周秉义提离婚","word":"郝冬梅向周秉义提离婚"},{"url":"https://so.toutiao.com/search?keyword=《婚姻的两种猜想》谁是喜剧担当","word":"《婚姻的两种猜想》谁是喜剧担当"},{"url":"https://so.toutiao.com/search?keyword=俄方：目标是阻止乌克兰新纳粹政权","word":"俄方：目标是阻止乌克兰新纳粹政权"},{"url":"https://so.toutiao.com/search?keyword=香港歌手张伟文病情恶化","word":"香港歌手张伟文病情恶化"},{"url":"https://so.toutiao.com/search?keyword=海南三亚新增本土确诊1例","word":"海南三亚新增本土确诊1例"},{"url":"https://so.toutiao.com/search?keyword=发改委副主任唐登杰任民政部部长","word":"发改委副主任唐登杰任民政部部长"},{"url":"https://so.toutiao.com/search?keyword=普京：将核遏制力量提至特殊战备状态","word":"普京：将核遏制力量提至特殊战备状态"},{"url":"https://so.toutiao.com/search?keyword=湖人疯狂失误惨败鹈鹕","word":"湖人疯狂失误惨败鹈鹕"},{"url":"https://so.toutiao.com/search?keyword=俄乌冲突会波及哪些上市公司","word":"俄乌冲突会波及哪些上市公司"},{"url":"https://so.toutiao.com/search?keyword=德国宣布大幅增加国防开支","word":"德国宣布大幅增加国防开支"},{"url":"https://so.toutiao.com/search?keyword=国际足联：俄罗斯比赛改中立场地","word":"国际足联：俄罗斯比赛改中立场地"},{"url":"https://so.toutiao.com/search?keyword=退役军人优待证“朋友圈”又扩大","word":"退役军人优待证“朋友圈”又扩大"},{"url":"https://so.toutiao.com/search?keyword=香港不排除全民检测期间实施禁足令","word":"香港不排除全民检测期间实施禁足令"},{"url":"https://so.toutiao.com/search?keyword=河北邯郸数百人卷入出生证买卖大案","word":"河北邯郸数百人卷入出生证买卖大案"},{"url":"https://so.toutiao.com/search?keyword=大量乌克兰难民逃往边境","word":"大量乌克兰难民逃往边境"},{"url":"https://so.toutiao.com/search?keyword=欧盟今起对俄罗斯关闭领空","word":"欧盟今起对俄罗斯关闭领空"},{"url":"https://so.toutiao.com/search?keyword=乌方：基辅遭3枚导弹袭击","word":"乌方：基辅遭3枚导弹袭击"},{"url":"https://so.toutiao.com/search?keyword=我国人均GDP超过世界人均水平","word":"我国人均GDP超过世界人均水平"},{"url":"https://so.toutiao.com/search?keyword=西南大学教师被指猥亵人体模特","word":"西南大学教师被指猥亵人体模特"},{"url":"https://so.toutiao.com/search?keyword=俄乌冲突有3个没想到","word":"俄乌冲突有3个没想到"},{"url":"https://so.toutiao.com/search?keyword=基辅一中国留学生下楼倒垃圾遭盘查","word":"基辅一中国留学生下楼倒垃圾遭盘查"},{"url":"https://so.toutiao.com/search?keyword=深圳新增30例本土确诊、6例无症状","word":"深圳新增30例本土确诊、6例无症状"},{"url":"https://so.toutiao.com/search?keyword=数字货币概念股信安世纪等多股涨停","word":"数字货币概念股信安世纪等多股涨停"},{"url":"https://so.toutiao.com/search?keyword=俄乌冲突将如何影响国际空间站合作","word":"俄乌冲突将如何影响国际空间站合作"},{"url":"https://so.toutiao.com/search?keyword=山东烟台新增1例无症状+曾乘高铁","word":"山东烟台新增1例无症状 曾乘高铁"},{"url":"https://so.toutiao.com/search?keyword=22星“拼车”上太空+功能各有不同","word":"22星“拼车”上太空 功能各有不同"},{"url":"https://so.toutiao.com/search?keyword=日本一调查：中国人对日好感度下滑","word":"日本一调查：中国人对日好感度下滑"},{"url":"https://so.toutiao.com/search?keyword=俄罗斯航空公司暂停运营欧洲航线","word":"俄罗斯航空公司暂停运营欧洲航线"},{"url":"https://so.toutiao.com/search?keyword=勇士惨遭独行侠大逆转","word":"勇士惨遭独行侠大逆转"},{"url":"https://so.toutiao.com/search?keyword=武大学生自研微纳卫星成功发射","word":"武大学生自研微纳卫星成功发射"},{"url":"https://so.toutiao.com/search?keyword=决战基辅+乌克兰靠巷战难以支撑","word":"决战基辅 乌克兰靠巷战难以支撑"},{"url":"https://so.toutiao.com/search?keyword=欧盟委员会主席称希望乌克兰入欧盟","word":"欧盟委员会主席称希望乌克兰入欧盟"},{"url":"https://so.toutiao.com/search?keyword=“通村村”打通农村出行最后一公里","word":"“通村村”打通农村出行最后一公里"},{"url":"https://so.toutiao.com/search?keyword=天津新增本土确诊9例、无症状1例","word":"天津新增本土确诊9例、无症状1例"},{"url":"https://so.toutiao.com/search?keyword=媒体评陕西一副校长殴打学生被停职","word":"媒体评陕西一副校长殴打学生被停职"},{"url":"https://so.toutiao.com/search?keyword=俄航航班在接近美国领空时折返","word":"俄航航班在接近美国领空时折返"},{"url":"https://so.toutiao.com/search?keyword=现役士兵衔级制度草案提请审议","word":"现役士兵衔级制度草案提请审议"},{"url":"https://so.toutiao.com/search?keyword=法国记者控诉乌克兰轰炸本国平民","word":"法国记者控诉乌克兰轰炸本国平民"},{"url":"https://so.toutiao.com/search?keyword=俄乌战事：战争背后的战争","word":"俄乌战事：战争背后的战争"},{"url":"https://so.toutiao.com/search?keyword=苗苗说想好好学英语","word":"苗苗说想好好学英语"},{"url":"https://so.toutiao.com/search?keyword=世界最大运输机安-225遭俄军摧毁","word":"世界最大运输机安-225遭俄军摧毁"},{"url":"https://so.toutiao.com/search?keyword=德总理：俄使欧洲安全处于威胁之下","word":"德总理：俄使欧洲安全处于威胁之下"},{"url":"https://so.toutiao.com/search?keyword=广东东莞增9例本土确诊、10例无症状","word":"广东东莞增9例本土确诊、10例无症状"},{"url":"https://so.toutiao.com/search?keyword=港媒：拿不到中国货愁坏美国唐人街","word":"港媒：拿不到中国货愁坏美国唐人街"},{"url":"https://so.toutiao.com/search?keyword=世行前行长：美中需要新上海公报","word":"世行前行长：美中需要新上海公报"},{"url":"https://so.toutiao.com/search?keyword=美学者反思：北约扩张是致命错误","word":"美学者反思：北约扩张是致命错误"},{"url":"https://so.toutiao.com/search?keyword=《人世间》从家的变化看中国的发展","word":"《人世间》从家的变化看中国的发展"},{"url":"https://so.toutiao.com/search?keyword=乌克兰在海牙国际法庭对俄提起诉讼","word":"乌克兰在海牙国际法庭对俄提起诉讼"},{"url":"https://so.toutiao.com/search?keyword=俄方：乌代表团赴白俄罗斯与俄谈判","word":"俄方：乌代表团赴白俄罗斯与俄谈判"},{"url":"https://so.toutiao.com/search?keyword=俄方首次公告军事行动中有俄军伤亡","word":"俄方首次公告军事行动中有俄军伤亡"},{"url":"https://so.toutiao.com/search?keyword=车臣领导人呼吁在乌全境开展军事行动","word":"车臣领导人呼吁在乌全境开展军事行动"},{"url":"https://so.toutiao.com/search?keyword=倪妮连续8年为Angelababy庆生","word":"倪妮连续8年为Angelababy庆生"},{"url":"https://so.toutiao.com/search?keyword=杨幂发文为Angelababy庆生","word":"杨幂发文为Angelababy庆生"},{"url":"https://so.toutiao.com/search?keyword=胡连馨：为拍《人世间》向妈妈取经","word":"胡连馨：为拍《人世间》向妈妈取经"},{"url":"https://so.toutiao.com/search?keyword=普京向在乌的俄特种作战部队致谢","word":"普京向在乌的俄特种作战部队致谢"},{"url":"https://so.toutiao.com/search?keyword=至少15万乌克兰人已前往邻国避难","word":"至少15万乌克兰人已前往邻国避难"},{"url":"https://so.toutiao.com/search?keyword=一图看懂华为智慧办公春季发布会","word":"一图看懂华为智慧办公春季发布会"},{"url":"https://so.toutiao.com/search?keyword=英外交大臣：乌克兰冲突或持续数年","word":"英外交大臣：乌克兰冲突或持续数年"},{"url":"https://so.toutiao.com/search?keyword=考场救人的安徽儿科医生考研落榜","word":"考场救人的安徽儿科医生考研落榜"},{"url":"https://so.toutiao.com/search?keyword=小S透露大S在婚姻里过得并不快乐","word":"小S透露大S在婚姻里过得并不快乐"},{"url":"https://so.toutiao.com/search?keyword=欧盟希望通过谈判解决俄乌冲突","word":"欧盟希望通过谈判解决俄乌冲突"},{"url":"https://so.toutiao.com/search?keyword=安倍讨论日本部署美国核武器","word":"安倍讨论日本部署美国核武器"},{"url":"https://so.toutiao.com/search?keyword=媒体探访：上海再现百人排队买房","word":"媒体探访：上海再现百人排队买房"},{"url":"https://so.toutiao.com/search?keyword=基辅周边地区爆炸升起巨大蘑菇云","word":"基辅周边地区爆炸升起巨大蘑菇云"},{"url":"https://so.toutiao.com/search?keyword=恩比德37分哈登三双+76人胜尼克斯","word":"恩比德37分哈登三双 76人胜尼克斯"},{"url":"https://so.toutiao.com/search?keyword=俄官员：谈判期间不会停止军事行动","word":"俄官员：谈判期间不会停止军事行动"},{"url":"https://so.toutiao.com/search?keyword=媒体谈就业市场“35岁门槛”","word":"媒体谈就业市场“35岁门槛”"},{"url":"https://so.toutiao.com/search?keyword=“RT女主播公开指责俄国”系旧闻","word":"“RT女主播公开指责俄国”系旧闻"},{"url":"https://so.toutiao.com/search?keyword=张雨绮滑雪被偶遇","word":"张雨绮滑雪被偶遇"},{"url":"https://so.toutiao.com/search?keyword=日本政府将冻结普京等俄官员资产","word":"日本政府将冻结普京等俄官员资产"},{"url":"https://so.toutiao.com/search?keyword=曹格妻子晒与13岁儿子Joe合照","word":"曹格妻子晒与13岁儿子Joe合照"},{"url":"https://so.toutiao.com/search?keyword=欧盟或将向乌提供资金购买军事物资","word":"欧盟或将向乌提供资金购买军事物资"},{"url":"https://so.toutiao.com/search?keyword=游客西藏自驾租车直接上4S店提新车","word":"游客西藏自驾租车直接上4S店提新车"},{"url":"https://so.toutiao.com/search?keyword=我驻乌使馆开始核对中国公民信息","word":"我驻乌使馆开始核对中国公民信息"},{"url":"https://so.toutiao.com/search?keyword=拜登回应特朗普此前称赞普京","word":"拜登回应特朗普此前称赞普京"},{"url":"https://so.toutiao.com/search?keyword=400名中国留学生在乌克兰抱团取暖","word":"400名中国留学生在乌克兰抱团取暖"},{"url":"https://so.toutiao.com/search?keyword=主持人张蕾晒旗袍美照","word":"主持人张蕾晒旗袍美照"},{"url":"https://so.toutiao.com/search?keyword=联赛杯：利物浦点球击败切尔西夺冠","word":"联赛杯：利物浦点球击败切尔西夺冠"},{"url":"https://so.toutiao.com/search?keyword=在乌留学生：看到妈妈80个未接来电","word":"在乌留学生：看到妈妈80个未接来电"},{"url":"https://so.toutiao.com/search?keyword=乌方：战事集中在哈尔科夫和基辅","word":"乌方：战事集中在哈尔科夫和基辅"},{"url":"https://so.toutiao.com/search?keyword=乌克兰边境上演一幕幕离别","word":"乌克兰边境上演一幕幕离别"},{"url":"https://so.toutiao.com/search?keyword=乌总统要求瑞士联邦主席斡旋乌危机","word":"乌总统要求瑞士联邦主席斡旋乌危机"},{"url":"https://so.toutiao.com/search?keyword=“金融核弹”+SWIFT威力究竟有多大","word":"“金融核弹” SWIFT威力究竟有多大"},{"url":"https://so.toutiao.com/search?keyword=乌方：俄乌会谈将不带先决条件","word":"乌方：俄乌会谈将不带先决条件"},{"url":"https://so.toutiao.com/search?keyword=被踢出SWIFT+俄罗斯有哪些反制办法","word":"被踢出SWIFT 俄罗斯有哪些反制办法"},{"url":"https://so.toutiao.com/search?keyword=乌方宣布成立由外籍人士组成的部队","word":"乌方宣布成立由外籍人士组成的部队"},{"url":"https://so.toutiao.com/search?keyword=俄乌之战70小时发生了什么","word":"俄乌之战70小时发生了什么"},{"url":"https://so.toutiao.com/search?keyword=拜登谈对俄两选项：制裁或世界大战","word":"拜登谈对俄两选项：制裁或世界大战"},{"url":"https://so.toutiao.com/search?keyword=基辅“血战”进行时","word":"基辅“血战”进行时"},{"url":"https://so.toutiao.com/search?keyword=俄称乌军一防空导弹团投降+471人被俘","word":"俄称乌军一防空导弹团投降 471人被俘"},{"url":"https://so.toutiao.com/search?keyword=唐驳虎：俄军全向攻击+使用重武器","word":"唐驳虎：俄军全向攻击 使用重武器"},{"url":"https://so.toutiao.com/search?keyword=《人世间》里没有纯粹的坏人","word":"《人世间》里没有纯粹的坏人"},{"url":"https://so.toutiao.com/search?keyword=吴奇隆刘诗诗辟谣婚变传闻","word":"吴奇隆刘诗诗辟谣婚变传闻"},{"url":"https://so.toutiao.com/search?keyword=网红唐痘痘因急性胰腺炎离世","word":"网红唐痘痘因急性胰腺炎离世"},{"url":"https://so.toutiao.com/search?keyword=专家：俄乌冲突成持久战可能性不大","word":"专家：俄乌冲突成持久战可能性不大"},{"url":"https://so.toutiao.com/search?keyword=娱乐圈里有哪些让人羡慕的友谊","word":"娱乐圈里有哪些让人羡慕的友谊"},{"url":"https://so.toutiao.com/search?keyword=欧洲五国宣布对俄航班关闭领空","word":"欧洲五国宣布对俄航班关闭领空"},{"url":"https://so.toutiao.com/search?keyword=疫情下香港明星做生意有多受打击","word":"疫情下香港明星做生意有多受打击"},{"url":"https://so.toutiao.com/search?keyword=《人世间》终于好起来了","word":"《人世间》终于好起来了"},{"url":"https://so.toutiao.com/search?keyword=东莞大朗新增9例确诊病例","word":"东莞大朗新增9例确诊病例"},{"url":"https://so.toutiao.com/search?keyword=3月起一批新规将正式落地实施","word":"3月起一批新规将正式落地实施"},{"url":"https://so.toutiao.com/search?keyword=《相逢时节》郝青林有多气人","word":"《相逢时节》郝青林有多气人"},{"url":"https://so.toutiao.com/search?keyword=乌克兰官员称基辅仍在乌军控制下","word":"乌克兰官员称基辅仍在乌军控制下"},{"url":"https://so.toutiao.com/search?keyword=乌方：俄军已进入哈尔科夫市中心","word":"乌方：俄军已进入哈尔科夫市中心"},{"url":"https://so.toutiao.com/search?keyword=影视剧中让人印象深刻的老戏骨","word":"影视剧中让人印象深刻的老戏骨"},{"url":"https://so.toutiao.com/search?keyword=王毅：中方不赞成用制裁解决问题","word":"王毅：中方不赞成用制裁解决问题"},{"url":"https://so.toutiao.com/search?keyword=俄军为何不采取斩首行动","word":"俄军为何不采取斩首行动"},{"url":"https://so.toutiao.com/search?keyword=《人世间》里的温情瞬间","word":"《人世间》里的温情瞬间"},{"url":"https://so.toutiao.com/search?keyword=俄军方指美军无人机涉入乌克兰战事","word":"俄军方指美军无人机涉入乌克兰战事"},{"url":"https://so.toutiao.com/search?keyword=网曝张学友在观音莲花瓣上刻名","word":"网曝张学友在观音莲花瓣上刻名"},{"url":"https://so.toutiao.com/search?keyword=乌克兰第二大城市发生炮战","word":"乌克兰第二大城市发生炮战"},{"url":"https://so.toutiao.com/search?keyword=乌克兰基辅一核废料埋藏点被炸","word":"乌克兰基辅一核废料埋藏点被炸"},{"url":"https://so.toutiao.com/search?keyword=古巴外交部批美国推动北约东扩","word":"古巴外交部批美国推动北约东扩"},{"url":"https://so.toutiao.com/search?keyword=乌克兰国防部长：已粉碎俄军计划","word":"乌克兰国防部长：已粉碎俄军计划"},{"url":"https://so.toutiao.com/search?keyword=中使馆：除包机外正协调其他方式撤侨","word":"中使馆：除包机外正协调其他方式撤侨"},{"url":"https://so.toutiao.com/search?keyword=车臣领导人驳斥部队被乌歼灭消息","word":"车臣领导人驳斥部队被乌歼灭消息"},{"url":"https://so.toutiao.com/search?keyword=基辅市长：大部分俄军距基辅20公里","word":"基辅市长：大部分俄军距基辅20公里"},{"url":"https://so.toutiao.com/search?keyword=乌总统：国际已建立强大联盟支持乌","word":"乌总统：国际已建立强大联盟支持乌"},{"url":"https://so.toutiao.com/search?keyword=联合国：乌克兰平民至少64死240伤","word":"联合国：乌克兰平民至少64死240伤"},{"url":"https://so.toutiao.com/search?keyword=中国驻乌大使辟谣人不在基辅","word":"中国驻乌大使辟谣人不在基辅"},{"url":"https://so.toutiao.com/search?keyword=乌克兰外交官：我被德国气哭了","word":"乌克兰外交官：我被德国气哭了"},{"url":"https://so.toutiao.com/search?keyword=立陶宛军事援助抵达乌克兰","word":"立陶宛军事援助抵达乌克兰"},{"url":"https://so.toutiao.com/search?keyword=香港新增病例26026例+新增死亡83例","word":"香港新增病例26026例 新增死亡83例"},{"url":"https://so.toutiao.com/search?keyword=车臣领导人社交媒体账户被封","word":"车臣领导人社交媒体账户被封"},{"url":"https://so.toutiao.com/search?keyword=西方多国对乌军事援助","word":"西方多国对乌军事援助"},{"url":"https://so.toutiao.com/search?keyword=白俄罗斯：可能对乌克兰采取行动","word":"白俄罗斯：可能对乌克兰采取行动"},{"url":"https://so.toutiao.com/search?keyword=乌克兰将关与俄罗斯和白俄罗斯边界","word":"乌克兰将关与俄罗斯和白俄罗斯边界"},{"url":"https://so.toutiao.com/search?keyword=俄罗斯飞机被禁止进入德国领空","word":"俄罗斯飞机被禁止进入德国领空"},{"url":"https://so.toutiao.com/search?keyword=武汉今日新增2例确诊","word":"武汉今日新增2例确诊"},{"url":"https://so.toutiao.com/search?keyword=乌克兰哈尔科夫市区巷战画面曝光","word":"乌克兰哈尔科夫市区巷战画面曝光"},{"url":"https://so.toutiao.com/search?keyword=英首相：愿意接收来自乌克兰的难民","word":"英首相：愿意接收来自乌克兰的难民"},{"url":"https://so.toutiao.com/search?keyword=基辅副市长：基辅完全在乌军控制下","word":"基辅副市长：基辅完全在乌军控制下"},{"url":"https://so.toutiao.com/search?keyword=盘点俄对乌作战的两种“王牌武器”","word":"盘点俄对乌作战的两种“王牌武器”"}]