[{"url":"https://so.toutiao.com/search?keyword=媒体：公布打人事件受害人近况不宜迟","word":"媒体：公布打人事件受害人近况不宜迟"},{"url":"https://so.toutiao.com/search?keyword=世界男排联赛：中国与法国比赛取消","word":"世界男排联赛：中国与法国比赛取消"},{"url":"https://so.toutiao.com/search?keyword=中国成功实施陆基中段反导拦截技术试验","word":"中国成功实施陆基中段反导拦截技术试验"},{"url":"https://so.toutiao.com/search?keyword=钟南山没打疫苗？查询方式不靠谱","word":"钟南山没打疫苗？查询方式不靠谱"},{"url":"https://so.toutiao.com/search?keyword=美军向太平洋发射4枚洲际弹道导弹","word":"美军向太平洋发射4枚洲际弹道导弹"},{"url":"https://so.toutiao.com/search?keyword=官方辟谣常州一院骨科医生团建嫖娼","word":"官方辟谣常州一院骨科医生团建嫖娼"},{"url":"https://so.toutiao.com/search?keyword=新财富集团是如何操控13家村镇银行的","word":"新财富集团是如何操控13家村镇银行的"},{"url":"https://so.toutiao.com/search?keyword=腾讯高位“清仓式”减持新东方在线","word":"腾讯高位“清仓式”减持新东方在线"},{"url":"https://so.toutiao.com/search?keyword=辽宁盘锦公安局原局长申海青被逮捕","word":"辽宁盘锦公安局原局长申海青被逮捕"},{"url":"https://so.toutiao.com/search?keyword=原国家女排主教练李耀先逝世","word":"原国家女排主教练李耀先逝世"},{"url":"https://so.toutiao.com/search?keyword=拥有陆基中段反导拦截技术有多重要","word":"拥有陆基中段反导拦截技术有多重要"},{"url":"https://so.toutiao.com/search?keyword=中方赞赏卡塔尔恪守一个中国原则","word":"中方赞赏卡塔尔恪守一个中国原则"},{"url":"https://so.toutiao.com/search?keyword=南方暴雨北方高温即将终结","word":"南方暴雨北方高温即将终结"},{"url":"https://so.toutiao.com/search?keyword=上海火灾救人外卖小哥曾是企业副总","word":"上海火灾救人外卖小哥曾是企业副总"},{"url":"https://so.toutiao.com/search?keyword=四地高新区升为“国家级”","word":"四地高新区升为“国家级”"},{"url":"https://so.toutiao.com/search?keyword=江苏省委原副书记张敬华被逮捕","word":"江苏省委原副书记张敬华被逮捕"},{"url":"https://so.toutiao.com/search?keyword=中方重申在台湾海峡享有主权","word":"中方重申在台湾海峡享有主权"},{"url":"https://so.toutiao.com/search?keyword=中国公司在骂声中造芯片","word":"中国公司在骂声中造芯片"},{"url":"https://so.toutiao.com/search?keyword=克林顿承认曾派特工寻找外星人","word":"克林顿承认曾派特工寻找外星人"},{"url":"https://so.toutiao.com/search?keyword=俞敏洪给董宇辉颁发董事长特别奖","word":"俞敏洪给董宇辉颁发董事长特别奖"},{"url":"https://so.toutiao.com/search?keyword=中国男排因新冠无法参赛被判0-3负","word":"中国男排因新冠无法参赛被判0-3负"},{"url":"https://so.toutiao.com/search?keyword=北京一病例出现症状未报备致5人感染","word":"北京一病例出现症状未报备致5人感染"},{"url":"https://so.toutiao.com/search?keyword=杨雪说江玉燕在甄嬛传里能活到最后","word":"杨雪说江玉燕在甄嬛传里能活到最后"},{"url":"https://so.toutiao.com/search?keyword=河南提现难银行储户：不认识新财富","word":"河南提现难银行储户：不认识新财富"},{"url":"https://so.toutiao.com/search?keyword=俞敏洪确认有机构挖董宇辉","word":"俞敏洪确认有机构挖董宇辉"},{"url":"https://so.toutiao.com/search?keyword=梅志强回乡与25年未见长辈认亲","word":"梅志强回乡与25年未见长辈认亲"},{"url":"https://so.toutiao.com/search?keyword=男子阻止村霸抢地被碾死？警方回应","word":"男子阻止村霸抢地被碾死？警方回应"},{"url":"https://so.toutiao.com/search?keyword=《难忘今宵》词作者乔羽因病逝世","word":"《难忘今宵》词作者乔羽因病逝世"},{"url":"https://so.toutiao.com/search?keyword=两部门约谈中石化集团公司","word":"两部门约谈中石化集团公司"},{"url":"https://so.toutiao.com/search?keyword=为啥戴手套吃小龙虾还是满手油","word":"为啥戴手套吃小龙虾还是满手油"},{"url":"https://so.toutiao.com/search?keyword=北京人艺院长任鸣逝世%20享年62岁","word":"北京人艺院长任鸣逝世 享年62岁"},{"url":"https://so.toutiao.com/search?keyword=官方：为夜宵店被打老板申报见义勇为","word":"官方：为夜宵店被打老板申报见义勇为"},{"url":"https://so.toutiao.com/search?keyword=李鸿忠当选天津市委书记","word":"李鸿忠当选天津市委书记"},{"url":"https://so.toutiao.com/search?keyword=NASA新发现两个“超级地球”","word":"NASA新发现两个“超级地球”"},{"url":"https://so.toutiao.com/search?keyword=记者深入顿巴斯战区：俄乌激烈对峙","word":"记者深入顿巴斯战区：俄乌激烈对峙"},{"url":"https://so.toutiao.com/search?keyword=北向资金出逃近百亿","word":"北向资金出逃近百亿"},{"url":"https://so.toutiao.com/search?keyword=中国汽车出口量猛增的背后","word":"中国汽车出口量猛增的背后"},{"url":"https://so.toutiao.com/search?keyword=俄外交部召见立陶宛驻俄临时代办","word":"俄外交部召见立陶宛驻俄临时代办"},{"url":"https://so.toutiao.com/search?keyword=媒体揭河南新财富集团实控人套现手法","word":"媒体揭河南新财富集团实控人套现手法"},{"url":"https://so.toutiao.com/search?keyword=丧偶女性有权做试管婴儿吗","word":"丧偶女性有权做试管婴儿吗"},{"url":"https://so.toutiao.com/search?keyword=两所985大学同一校长？华工：属实","word":"两所985大学同一校长？华工：属实"},{"url":"https://so.toutiao.com/search?keyword=李邑飞当选新疆生产建设兵团党委书记","word":"李邑飞当选新疆生产建设兵团党委书记"},{"url":"https://so.toutiao.com/search?keyword=美得州共和党人拒认拜登为合法总统","word":"美得州共和党人拒认拜登为合法总统"},{"url":"https://so.toutiao.com/search?keyword=爷爷给刚出生的孙女买30多条裙子","word":"爷爷给刚出生的孙女买30多条裙子"},{"url":"https://so.toutiao.com/search?keyword=德总理访乌带着的公文包有何玄机","word":"德总理访乌带着的公文包有何玄机"},{"url":"https://so.toutiao.com/search?keyword=南方四省现特大暴雨","word":"南方四省现特大暴雨"},{"url":"https://so.toutiao.com/search?keyword=男子以为朋友喝醉去世狂做人工呼吸","word":"男子以为朋友喝醉去世狂做人工呼吸"},{"url":"https://so.toutiao.com/search?keyword=文在寅晒养老生活：下地采摘生菜","word":"文在寅晒养老生活：下地采摘生菜"},{"url":"https://so.toutiao.com/search?keyword=王传君拒绝宋丹丹提议","word":"王传君拒绝宋丹丹提议"},{"url":"https://so.toutiao.com/search?keyword=多地入境人员缩短隔离期意味着什么","word":"多地入境人员缩短隔离期意味着什么"},{"url":"https://so.toutiao.com/search?keyword=董宇辉也有编不下去的时候","word":"董宇辉也有编不下去的时候"},{"url":"https://so.toutiao.com/search?keyword=河南新财富集团涉嫌相关犯罪11年","word":"河南新财富集团涉嫌相关犯罪11年"},{"url":"https://so.toutiao.com/search?keyword=泽连斯基：不会将乌南部拱手让人","word":"泽连斯基：不会将乌南部拱手让人"},{"url":"https://so.toutiao.com/search?keyword=直播连线上海石化火灾喊话骑手","word":"直播连线上海石化火灾喊话骑手"},{"url":"https://so.toutiao.com/search?keyword=钟南山没打疫苗？网传查询方式不靠谱","word":"钟南山没打疫苗？网传查询方式不靠谱"},{"url":"https://so.toutiao.com/search?keyword=凌晨两点后还能放心吃夜宵吗","word":"凌晨两点后还能放心吃夜宵吗"},{"url":"https://so.toutiao.com/search?keyword=本轮高温天气还要持续多久","word":"本轮高温天气还要持续多久"},{"url":"https://so.toutiao.com/search?keyword=人民网：赋红码一时爽后果必须扛","word":"人民网：赋红码一时爽后果必须扛"},{"url":"https://so.toutiao.com/search?keyword=东方甄选负责人：选主播更看重内涵","word":"东方甄选负责人：选主播更看重内涵"},{"url":"https://so.toutiao.com/search?keyword=明日夏至","word":"明日夏至"},{"url":"https://so.toutiao.com/search?keyword=为人民提供全方位全周期健康服务","word":"为人民提供全方位全周期健康服务"},{"url":"https://so.toutiao.com/search?keyword=珠海因疫情封控市民连夜离开","word":"珠海因疫情封控市民连夜离开"},{"url":"https://so.toutiao.com/search?keyword=台媒：10架次解放军军机昨进入台空域","word":"台媒：10架次解放军军机昨进入台空域"},{"url":"https://so.toutiao.com/search?keyword=女子3个月不洗头致头发打结梳不开","word":"女子3个月不洗头致头发打结梳不开"},{"url":"https://so.toutiao.com/search?keyword=博主：周琦若回CBA大概率去上海队","word":"博主：周琦若回CBA大概率去上海队"},{"url":"https://so.toutiao.com/search?keyword=河南村镇银行“影子老板”疑已赴美","word":"河南村镇银行“影子老板”疑已赴美"},{"url":"https://so.toutiao.com/search?keyword=乌称白俄军队大规模参战可能性不大","word":"乌称白俄军队大规模参战可能性不大"},{"url":"https://so.toutiao.com/search?keyword=中超：河南0-0亚泰开局五轮不败","word":"中超：河南0-0亚泰开局五轮不败"},{"url":"https://so.toutiao.com/search?keyword=初二学生网购花光母亲12万手术费","word":"初二学生网购花光母亲12万手术费"},{"url":"https://so.toutiao.com/search?keyword=中国实施陆基中段反导拦截技术试验","word":"中国实施陆基中段反导拦截技术试验"},{"url":"https://so.toutiao.com/search?keyword=王林清受贿案二审维持14年原判","word":"王林清受贿案二审维持14年原判"},{"url":"https://so.toutiao.com/search?keyword=安徽蚌埠市教育局原局长刘玉泽被查","word":"安徽蚌埠市教育局原局长刘玉泽被查"},{"url":"https://so.toutiao.com/search?keyword=6元一根“新东方”玉米%20农民赚多少","word":"6元一根“新东方”玉米 农民赚多少"},{"url":"https://so.toutiao.com/search?keyword=女排世界排名：中国队位居第三","word":"女排世界排名：中国队位居第三"},{"url":"https://so.toutiao.com/search?keyword=乌外长：若没有武器将使用铁锹作战","word":"乌外长：若没有武器将使用铁锹作战"},{"url":"https://so.toutiao.com/search?keyword=男子无证驾驶撞塌价值170万牌坊","word":"男子无证驾驶撞塌价值170万牌坊"},{"url":"https://so.toutiao.com/search?keyword=众星悼念任鸣","word":"众星悼念任鸣"},{"url":"https://so.toutiao.com/search?keyword=自制药救子父亲谈实验过程","word":"自制药救子父亲谈实验过程"},{"url":"https://so.toutiao.com/search?keyword=女子跪谢拾金不昧摊主","word":"女子跪谢拾金不昧摊主"},{"url":"https://so.toutiao.com/search?keyword=河南多家村镇银行开展客户资金登记","word":"河南多家村镇银行开展客户资金登记"},{"url":"https://so.toutiao.com/search?keyword=库里总决赛共78次突破砍下47分","word":"库里总决赛共78次突破砍下47分"},{"url":"https://so.toutiao.com/search?keyword=李谷一缅怀乔羽","word":"李谷一缅怀乔羽"},{"url":"https://so.toutiao.com/search?keyword=中超：谭龙错失良机%20亚泰0-0河南","word":"中超：谭龙错失良机 亚泰0-0河南"},{"url":"https://so.toutiao.com/search?keyword=《新闻联播》正在直播","word":"《新闻联播》正在直播"},{"url":"https://so.toutiao.com/search?keyword=吉林市所有客运车辆停运三天","word":"吉林市所有客运车辆停运三天"},{"url":"https://so.toutiao.com/search?keyword=董宇辉救活了新东方","word":"董宇辉救活了新东方"},{"url":"https://so.toutiao.com/search?keyword=男子起诉邻居：借走古董烟嘴32年不还","word":"男子起诉邻居：借走古董烟嘴32年不还"},{"url":"https://so.toutiao.com/search?keyword=足力健累计被执行总金额超1.32亿元","word":"足力健累计被执行总金额超1.32亿元"},{"url":"https://so.toutiao.com/search?keyword=中国歌剧舞剧院发布乔羽讣告","word":"中国歌剧舞剧院发布乔羽讣告"},{"url":"https://so.toutiao.com/search?keyword=人民网评董宇辉走红","word":"人民网评董宇辉走红"},{"url":"https://so.toutiao.com/search?keyword=北京昌平新增病例含学生和装修工人","word":"北京昌平新增病例含学生和装修工人"},{"url":"https://so.toutiao.com/search?keyword=上海社会面增2例感染者%202地升中风险","word":"上海社会面增2例感染者 2地升中风险"},{"url":"https://so.toutiao.com/search?keyword=云南一公安局院内长出大片牛肝菌","word":"云南一公安局院内长出大片牛肝菌"},{"url":"https://so.toutiao.com/search?keyword=台媒：台军雷霆2000火箭发射时爆炸","word":"台媒：台军雷霆2000火箭发射时爆炸"},{"url":"https://so.toutiao.com/search?keyword=多地低风险地区来返人员不再查验核酸","word":"多地低风险地区来返人员不再查验核酸"},{"url":"https://so.toutiao.com/search?keyword=台湾5.9级地震%20福建震感明显","word":"台湾5.9级地震 福建震感明显"},{"url":"https://so.toutiao.com/search?keyword=河南“取款难”银行储户：查不到余额","word":"河南“取款难”银行储户：查不到余额"},{"url":"https://so.toutiao.com/search?keyword=一分钟带你走近词作家乔羽","word":"一分钟带你走近词作家乔羽"},{"url":"https://so.toutiao.com/search?keyword=收评：创业板指放量大涨近2%","word":"收评：创业板指放量大涨近2%"},{"url":"https://so.toutiao.com/search?keyword=专家：尽早带爸妈接种带状疱疹疫苗","word":"专家：尽早带爸妈接种带状疱疹疫苗"},{"url":"https://so.toutiao.com/search?keyword=台湾花莲县发生5.9级地震","word":"台湾花莲县发生5.9级地震"},{"url":"https://so.toutiao.com/search?keyword=世界多地现罕见高温","word":"世界多地现罕见高温"},{"url":"https://so.toutiao.com/search?keyword=商品期货收盘黑色系全线大跌","word":"商品期货收盘黑色系全线大跌"},{"url":"https://so.toutiao.com/search?keyword=俄副总理称已在对乌行动中使用苏57","word":"俄副总理称已在对乌行动中使用苏57"},{"url":"https://so.toutiao.com/search?keyword=李玟聊《为歌而赞》新歌舞台首秀","word":"李玟聊《为歌而赞》新歌舞台首秀"},{"url":"https://so.toutiao.com/search?keyword=英军高官：做好再次在欧洲作战准备","word":"英军高官：做好再次在欧洲作战准备"},{"url":"https://so.toutiao.com/search?keyword=航天员入住中国空间站一年啦","word":"航天员入住中国空间站一年啦"},{"url":"https://so.toutiao.com/search?keyword=众星发文悼念乔羽","word":"众星发文悼念乔羽"},{"url":"https://so.toutiao.com/search?keyword=乔羽经典作品回顾","word":"乔羽经典作品回顾"},{"url":"https://so.toutiao.com/search?keyword=13人澳门入境珠海未落实防疫被拘","word":"13人澳门入境珠海未落实防疫被拘"},{"url":"https://so.toutiao.com/search?keyword=周杰伦新专辑名字","word":"周杰伦新专辑名字"},{"url":"https://so.toutiao.com/search?keyword=台湾新增确诊35632例%20死亡144例","word":"台湾新增确诊35632例 死亡144例"},{"url":"https://so.toutiao.com/search?keyword=新东方的“失败者们”现在怎么样了","word":"新东方的“失败者们”现在怎么样了"},{"url":"https://so.toutiao.com/search?keyword=经纪公司回应南柱赫校园暴力","word":"经纪公司回应南柱赫校园暴力"},{"url":"https://so.toutiao.com/search?keyword=武汉中考作文题揭晓","word":"武汉中考作文题揭晓"},{"url":"https://so.toutiao.com/search?keyword=河南新财富集团实控人套现手法揭秘","word":"河南新财富集团实控人套现手法揭秘"},{"url":"https://so.toutiao.com/search?keyword=谁为储户资金安全负责","word":"谁为储户资金安全负责"},{"url":"https://so.toutiao.com/search?keyword=邓刚公园盘老板看呆大爷大妈","word":"邓刚公园盘老板看呆大爷大妈"},{"url":"https://so.toutiao.com/search?keyword=天津21日起恢复实施机动车尾号限行","word":"天津21日起恢复实施机动车尾号限行"},{"url":"https://so.toutiao.com/search?keyword=蜜雪冰城回应雪王晒黑","word":"蜜雪冰城回应雪王晒黑"},{"url":"https://so.toutiao.com/search?keyword=31省份昨增本土14+10例","word":"31省份昨增本土14+10例"},{"url":"https://so.toutiao.com/search?keyword=你对周杰伦新专辑有哪些期待","word":"你对周杰伦新专辑有哪些期待"},{"url":"https://so.toutiao.com/search?keyword=俄军：发射口径导弹袭击乌军指挥所","word":"俄军：发射口径导弹袭击乌军指挥所"},{"url":"https://so.toutiao.com/search?keyword=北京丰台站首班车出发","word":"北京丰台站首班车出发"},{"url":"https://so.toutiao.com/search?keyword=C罗一家给迷你罗庆祝12岁生日","word":"C罗一家给迷你罗庆祝12岁生日"},{"url":"https://so.toutiao.com/search?keyword=孩子被困滑梯高处%20路人大哥冒险救人","word":"孩子被困滑梯高处 路人大哥冒险救人"},{"url":"https://so.toutiao.com/search?keyword=俄议员：莫斯科做好与北约对抗准备","word":"俄议员：莫斯科做好与北约对抗准备"},{"url":"https://so.toutiao.com/search?keyword=郑州出台大棚户区改造房票安置办法","word":"郑州出台大棚户区改造房票安置办法"},{"url":"https://so.toutiao.com/search?keyword=上海昨增本土确诊10例%20无症状3例","word":"上海昨增本土确诊10例 无症状3例"},{"url":"https://so.toutiao.com/search?keyword=午评：沪指震荡创业板指走高涨超2%","word":"午评：沪指震荡创业板指走高涨超2%"},{"url":"https://so.toutiao.com/search?keyword=张雨霏获100米蝶泳铜牌","word":"张雨霏获100米蝶泳铜牌"},{"url":"https://so.toutiao.com/search?keyword=多地缩短入境隔离时间","word":"多地缩短入境隔离时间"},{"url":"https://so.toutiao.com/search?keyword=WNBA：李月汝2分2板%20天空惜败狂热","word":"WNBA：李月汝2分2板 天空惜败狂热"},{"url":"https://so.toutiao.com/search?keyword=周冠宇刷新F1生涯最佳战绩","word":"周冠宇刷新F1生涯最佳战绩"},{"url":"https://so.toutiao.com/search?keyword=俄媒：北顿涅茨克部分乌武装人员投降","word":"俄媒：北顿涅茨克部分乌武装人员投降"},{"url":"https://so.toutiao.com/search?keyword=江苏昆山有序开放沪昆通勤","word":"江苏昆山有序开放沪昆通勤"},{"url":"https://so.toutiao.com/search?keyword=普京将以电话方式出席金砖国家峰会","word":"普京将以电话方式出席金砖国家峰会"},{"url":"https://so.toutiao.com/search?keyword=直击郑渝高铁开通首日","word":"直击郑渝高铁开通首日"},{"url":"https://so.toutiao.com/search?keyword=退休局长利用影响力受贿大肆敛财","word":"退休局长利用影响力受贿大肆敛财"},{"url":"https://so.toutiao.com/search?keyword=马克龙阵营未获议会绝对多数席位","word":"马克龙阵营未获议会绝对多数席位"},{"url":"https://so.toutiao.com/search?keyword=多家村镇银行取不出钱的第60天","word":"多家村镇银行取不出钱的第60天"},{"url":"https://so.toutiao.com/search?keyword=俄乌在蛇岛附近战事再起","word":"俄乌在蛇岛附近战事再起"},{"url":"https://so.toutiao.com/search?keyword=今年“618”线上线下消费表现如何","word":"今年“618”线上线下消费表现如何"},{"url":"https://so.toutiao.com/search?keyword=NBA得分最多父子组合：科比父子第1","word":"NBA得分最多父子组合：科比父子第1"},{"url":"https://so.toutiao.com/search?keyword=紫晶存储与炉石农商行传闻真相如何","word":"紫晶存储与炉石农商行传闻真相如何"},{"url":"https://so.toutiao.com/search?keyword=李健唱水中花","word":"李健唱水中花"},{"url":"https://so.toutiao.com/search?keyword=肝癌创新药易甘泰正式上市","word":"肝癌创新药易甘泰正式上市"},{"url":"https://so.toutiao.com/search?keyword=澳门新一轮疫情阳性病例增至31人","word":"澳门新一轮疫情阳性病例增至31人"},{"url":"https://so.toutiao.com/search?keyword=曝国米继续与切尔西谈卢卡库租借费","word":"曝国米继续与切尔西谈卢卡库租借费"},{"url":"https://so.toutiao.com/search?keyword=《难忘今宵》词作者乔羽去世","word":"《难忘今宵》词作者乔羽去世"},{"url":"https://so.toutiao.com/search?keyword=六旬女士称遭家暴欲离婚%20丈夫：想亲热","word":"六旬女士称遭家暴欲离婚 丈夫：想亲热"},{"url":"https://so.toutiao.com/search?keyword=男子翻出父亲国务院任命书%20有周恩来签字","word":"男子翻出父亲国务院任命书 有周恩来签字"},{"url":"https://so.toutiao.com/search?keyword=领导干部子女及其配偶经商也需报告","word":"领导干部子女及其配偶经商也需报告"},{"url":"https://so.toutiao.com/search?keyword=克林顿夫妇称美国民主濒临崩溃","word":"克林顿夫妇称美国民主濒临崩溃"},{"url":"https://so.toutiao.com/search?keyword=叙媒称美国驻军在叙利亚偷粮偷油","word":"叙媒称美国驻军在叙利亚偷粮偷油"},{"url":"https://so.toutiao.com/search?keyword=北京昨日新增本土4+1例","word":"北京昨日新增本土4+1例"},{"url":"https://so.toutiao.com/search?keyword=安徽80后厅官拟任省辖市市委常委","word":"安徽80后厅官拟任省辖市市委常委"},{"url":"https://so.toutiao.com/search?keyword=25%海外美侨考虑放弃美国国籍","word":"25%海外美侨考虑放弃美国国籍"},{"url":"https://so.toutiao.com/search?keyword=美在乌或再次触发“半途而废陷阱”","word":"美在乌或再次触发“半途而废陷阱”"},{"url":"https://so.toutiao.com/search?keyword=比特币跌穿1.8万美元%2015万人爆仓","word":"比特币跌穿1.8万美元 15万人爆仓"},{"url":"https://so.toutiao.com/search?keyword=自制药救子父亲：对父亲节有了期待","word":"自制药救子父亲：对父亲节有了期待"},{"url":"https://so.toutiao.com/search?keyword=挪威公主开18岁生日派对初戴王冠","word":"挪威公主开18岁生日派对初戴王冠"},{"url":"https://so.toutiao.com/search?keyword=特朗普警告可能发生第三次世界大战","word":"特朗普警告可能发生第三次世界大战"},{"url":"https://so.toutiao.com/search?keyword=晚睡晚起睡满8小时算不算熬夜","word":"晚睡晚起睡满8小时算不算熬夜"},{"url":"https://so.toutiao.com/search?keyword=河南高温之后将迎较大范围降雨","word":"河南高温之后将迎较大范围降雨"},{"url":"https://so.toutiao.com/search?keyword=北京：未按要求核检健康宝将弹窗","word":"北京：未按要求核检健康宝将弹窗"},{"url":"https://so.toutiao.com/search?keyword=贵州黄果树瀑布迎来今年最大水量","word":"贵州黄果树瀑布迎来今年最大水量"},{"url":"https://so.toutiao.com/search?keyword=花游双人技术自选王芊懿王柳懿夺冠","word":"花游双人技术自选王芊懿王柳懿夺冠"},{"url":"https://so.toutiao.com/search?keyword=印度一航班发动机空中起火紧急降落","word":"印度一航班发动机空中起火紧急降落"},{"url":"https://so.toutiao.com/search?keyword=4名武大医学生街头联手救人","word":"4名武大医学生街头联手救人"},{"url":"https://so.toutiao.com/search?keyword=东北流失的人口都去哪了","word":"东北流失的人口都去哪了"},{"url":"https://so.toutiao.com/search?keyword=沙特队夺得U23男足亚洲杯冠军","word":"沙特队夺得U23男足亚洲杯冠军"},{"url":"https://so.toutiao.com/search?keyword=杰森·特里：爵士仍是西部一流球队","word":"杰森·特里：爵士仍是西部一流球队"},{"url":"https://so.toutiao.com/search?keyword=618成为刺激消费的“关键一仗”","word":"618成为刺激消费的“关键一仗”"},{"url":"https://so.toutiao.com/search?keyword=佛山疑遭龙卷风：铁皮碎屑被卷起","word":"佛山疑遭龙卷风：铁皮碎屑被卷起"},{"url":"https://so.toutiao.com/search?keyword=哥伦比亚总统被法院下令软禁两天","word":"哥伦比亚总统被法院下令软禁两天"},{"url":"https://so.toutiao.com/search?keyword=伊斯特本草地赛郑钦文首轮出局","word":"伊斯特本草地赛郑钦文首轮出局"},{"url":"https://so.toutiao.com/search?keyword=疫情之下避孕套为何卖不动","word":"疫情之下避孕套为何卖不动"},{"url":"https://so.toutiao.com/search?keyword=哈萨克斯坦总统不承认卢甘斯克独立","word":"哈萨克斯坦总统不承认卢甘斯克独立"},{"url":"https://so.toutiao.com/search?keyword=河南新财富集团实控人已转外籍","word":"河南新财富集团实控人已转外籍"},{"url":"https://so.toutiao.com/search?keyword=国务院任命香港第六届政府主要官员","word":"国务院任命香港第六届政府主要官员"},{"url":"https://so.toutiao.com/search?keyword=大样本数据研究揭示奥密克戎重症率","word":"大样本数据研究揭示奥密克戎重症率"},{"url":"https://so.toutiao.com/search?keyword=世联赛：中国女排1-3不敌日本","word":"世联赛：中国女排1-3不敌日本"},{"url":"https://so.toutiao.com/search?keyword=美媒：美介入乌局势或再半途而废","word":"美媒：美介入乌局势或再半途而废"},{"url":"https://so.toutiao.com/search?keyword=媒体：五眼联盟炮制针对中国新谣言","word":"媒体：五眼联盟炮制针对中国新谣言"},{"url":"https://so.toutiao.com/search?keyword=孙海洋抖音直播时被小儿子偷亲","word":"孙海洋抖音直播时被小儿子偷亲"},{"url":"https://so.toutiao.com/search?keyword=浙江男子卖房后第二天就出拆迁公告","word":"浙江男子卖房后第二天就出拆迁公告"},{"url":"https://so.toutiao.com/search?keyword=伦敦爆发游行抗议生活成本上升","word":"伦敦爆发游行抗议生活成本上升"},{"url":"https://so.toutiao.com/search?keyword=小伙全奖直博%20论文致谢看哭网友","word":"小伙全奖直博 论文致谢看哭网友"},{"url":"https://so.toutiao.com/search?keyword=上海爆炸石化厂燃烧的特点是什么","word":"上海爆炸石化厂燃烧的特点是什么"},{"url":"https://so.toutiao.com/search?keyword=评论员详解福建舰多久能形成战斗力","word":"评论员详解福建舰多久能形成战斗力"},{"url":"https://so.toutiao.com/search?keyword=董宇辉否认直播有文案：张嘴就来","word":"董宇辉否认直播有文案：张嘴就来"},{"url":"https://so.toutiao.com/search?keyword=蜜雪冰城黑化","word":"蜜雪冰城黑化"},{"url":"https://so.toutiao.com/search?keyword=泽连斯基：乌被俘女军医被俄军释放","word":"泽连斯基：乌被俘女军医被俄军释放"},{"url":"https://so.toutiao.com/search?keyword=日本警方为富士山可能喷发做准备","word":"日本警方为富士山可能喷发做准备"},{"url":"https://so.toutiao.com/search?keyword=俞敏洪谈东方甄选：让大家吃好学好","word":"俞敏洪谈东方甄选：让大家吃好学好"},{"url":"https://so.toutiao.com/search?keyword=北京昌平新增病例密接34人","word":"北京昌平新增病例密接34人"},{"url":"https://so.toutiao.com/search?keyword=美是否放宽对华关税？拜登回应","word":"美是否放宽对华关税？拜登回应"},{"url":"https://so.toutiao.com/search?keyword=容祖儿回应香港音乐不如之前繁荣","word":"容祖儿回应香港音乐不如之前繁荣"},{"url":"https://so.toutiao.com/search?keyword=五家央企获批转为国有资本投资公司","word":"五家央企获批转为国有资本投资公司"},{"url":"https://so.toutiao.com/search?keyword=让人血压飙升的经典影视角色","word":"让人血压飙升的经典影视角色"},{"url":"https://so.toutiao.com/search?keyword=网飞新剧剧组出车祸两名演员死亡","word":"网飞新剧剧组出车祸两名演员死亡"},{"url":"https://so.toutiao.com/search?keyword=福建松溪出现历史最大洪水","word":"福建松溪出现历史最大洪水"},{"url":"https://so.toutiao.com/search?keyword=连战办公室：连战身体微恙住院","word":"连战办公室：连战身体微恙住院"},{"url":"https://so.toutiao.com/search?keyword=第78集团军某旅组织实弹演练","word":"第78集团军某旅组织实弹演练"},{"url":"https://so.toutiao.com/search?keyword=上海旅居史入苏州不再一刀切“7+7”","word":"上海旅居史入苏州不再一刀切“7+7”"},{"url":"https://so.toutiao.com/search?keyword=俄媒：亚速营头目已被送往俄罗斯","word":"俄媒：亚速营头目已被送往俄罗斯"},{"url":"https://so.toutiao.com/search?keyword=俄官员批立陶宛限制俄过境商品运输","word":"俄官员批立陶宛限制俄过境商品运输"},{"url":"https://so.toutiao.com/search?keyword=建业股份：公司董事长冯烈逝世","word":"建业股份：公司董事长冯烈逝世"},{"url":"https://so.toutiao.com/search?keyword=同煤集团三任董事长先后落马","word":"同煤集团三任董事长先后落马"},{"url":"https://so.toutiao.com/search?keyword=谷歌联合创始人布林再离婚","word":"谷歌联合创始人布林再离婚"},{"url":"https://so.toutiao.com/search?keyword=考试准考证出现文字错误%20官方致歉","word":"考试准考证出现文字错误 官方致歉"},{"url":"https://so.toutiao.com/search?keyword=人大代表：健康码应归国家统一管理","word":"人大代表：健康码应归国家统一管理"},{"url":"https://so.toutiao.com/search?keyword=英首相称世界或现“乌克兰疲劳症”","word":"英首相称世界或现“乌克兰疲劳症”"},{"url":"https://so.toutiao.com/search?keyword=日本高调展示地空导弹实弹训练","word":"日本高调展示地空导弹实弹训练"},{"url":"https://so.toutiao.com/search?keyword=广西或遇17年来最大洪水","word":"广西或遇17年来最大洪水"},{"url":"https://so.toutiao.com/search?keyword=俄方：乌疑似自导拍摄民宅被毁视频","word":"俄方：乌疑似自导拍摄民宅被毁视频"},{"url":"https://so.toutiao.com/search?keyword=女子卧床被丈夫照顾16年后愿意离婚","word":"女子卧床被丈夫照顾16年后愿意离婚"},{"url":"https://so.toutiao.com/search?keyword=图集：乌克兰马里乌波尔近况","word":"图集：乌克兰马里乌波尔近况"},{"url":"https://so.toutiao.com/search?keyword=北京检出1例社会面阳性在昌平区","word":"北京检出1例社会面阳性在昌平区"},{"url":"https://so.toutiao.com/search?keyword=广西两女孩骑车过漫水桥被冲走","word":"广西两女孩骑车过漫水桥被冲走"},{"url":"https://so.toutiao.com/search?keyword=广东韶关一消防车执行任务时遇洪水","word":"广东韶关一消防车执行任务时遇洪水"},{"url":"https://so.toutiao.com/search?keyword=京东618累计下单金额超3793亿元","word":"京东618累计下单金额超3793亿元"},{"url":"https://so.toutiao.com/search?keyword=比特币大崩盘%20华人首富身价缩水89%","word":"比特币大崩盘 华人首富身价缩水89%"},{"url":"https://so.toutiao.com/search?keyword=比特币是否进入至暗时刻","word":"比特币是否进入至暗时刻"},{"url":"https://so.toutiao.com/search?keyword=男子吃野蘑菇拿银镯试毒进医院","word":"男子吃野蘑菇拿银镯试毒进医院"},{"url":"https://so.toutiao.com/search?keyword=熊孩子爬小区雕像险被砸","word":"熊孩子爬小区雕像险被砸"},{"url":"https://so.toutiao.com/search?keyword=澳门新冠肺炎确诊病例升至21例","word":"澳门新冠肺炎确诊病例升至21例"},{"url":"https://so.toutiao.com/search?keyword=新东方暴涨10倍%20段永平赌赢了","word":"新东方暴涨10倍 段永平赌赢了"}]