[{"url":"https://so.toutiao.com/search?keyword=杭州原书记周江勇被双开：与资本勾连","word":"杭州原书记周江勇被双开：与资本勾连"},{"url":"https://so.toutiao.com/search?keyword=F35坠入南海+美媒害怕中国会打捞","word":"F35坠入南海 美媒害怕中国会打捞"},{"url":"https://so.toutiao.com/search?keyword=湖北一地积雪已达30厘米","word":"湖北一地积雪已达30厘米"},{"url":"https://so.toutiao.com/search?keyword=美专家：南海打捞坠毁战机需120天","word":"美专家：南海打捞坠毁战机需120天"},{"url":"https://so.toutiao.com/search?keyword=小孙女下车即被劝返+爷爷车站泪别","word":"小孙女下车即被劝返 爷爷车站泪别"},{"url":"https://so.toutiao.com/search?keyword=外卖员飞身拽回跳桥女子+本人回应","word":"外卖员飞身拽回跳桥女子 本人回应"},{"url":"https://so.toutiao.com/search?keyword=官员被情妇举报巨额财产来源不明","word":"官员被情妇举报巨额财产来源不明"},{"url":"https://so.toutiao.com/search?keyword=打工人返乡过年暖心瞬间","word":"打工人返乡过年暖心瞬间"},{"url":"https://so.toutiao.com/search?keyword=男子列车上索吻女乘客被拘5天","word":"男子列车上索吻女乘客被拘5天"},{"url":"https://so.toutiao.com/search?keyword=杭州确诊密接553人+已集中隔离管控","word":"杭州确诊密接553人 已集中隔离管控"},{"url":"https://so.toutiao.com/search?keyword=青岛一机场人员捡工卡遭客机碾压身亡","word":"青岛一机场人员捡工卡遭客机碾压身亡"},{"url":"https://so.toutiao.com/search?keyword=乌克兰愿与俄罗斯一战吗","word":"乌克兰愿与俄罗斯一战吗"},{"url":"https://so.toutiao.com/search?keyword=哈尔滨原市长宋希斌被查","word":"哈尔滨原市长宋希斌被查"},{"url":"https://so.toutiao.com/search?keyword=奥密克戎出现新变种：传播相对较快","word":"奥密克戎出现新变种：传播相对较快"},{"url":"https://so.toutiao.com/search?keyword=辅警查违章现场扫码收费？官方回应","word":"辅警查违章现场扫码收费？官方回应"},{"url":"https://so.toutiao.com/search?keyword=腾讯员工怼高管表彰加班+高管回应","word":"腾讯员工怼高管表彰加班 高管回应"},{"url":"https://so.toutiao.com/search?keyword=青岛航空通报机务遭碾死：沉痛哀悼","word":"青岛航空通报机务遭碾死：沉痛哀悼"},{"url":"https://so.toutiao.com/search?keyword=小年夜父亲偷偷给女儿点饭+备注看哭","word":"小年夜父亲偷偷给女儿点饭 备注看哭"},{"url":"https://so.toutiao.com/search?keyword=河北、黑龙江两省人大各一副部被查","word":"河北、黑龙江两省人大各一副部被查"},{"url":"https://so.toutiao.com/search?keyword=iOS微信8.0.18正式版发布","word":"iOS微信8.0.18正式版发布"},{"url":"https://so.toutiao.com/search?keyword=王子文晒瑜伽照","word":"王子文晒瑜伽照"},{"url":"https://so.toutiao.com/search?keyword=王凯谈患病经历","word":"王凯谈患病经历"},{"url":"https://so.toutiao.com/search?keyword=《奇葩说》辩手马剑越发文宣布离婚","word":"《奇葩说》辩手马剑越发文宣布离婚"},{"url":"https://so.toutiao.com/search?keyword=用复联的方式打开《开端》大结局","word":"用复联的方式打开《开端》大结局"},{"url":"https://so.toutiao.com/search?keyword=特斯拉被曝已起诉某千万粉丝大V","word":"特斯拉被曝已起诉某千万粉丝大V"},{"url":"https://so.toutiao.com/search?keyword=CBA：吉林险胜北控+姜宇星20+7","word":"CBA：吉林险胜北控 姜宇星20+7"},{"url":"https://so.toutiao.com/search?keyword=春节临近+持股过节还是持币过节","word":"春节临近 持股过节还是持币过节"},{"url":"https://so.toutiao.com/search?keyword=杭州外企工人确诊+曾参加公司年会","word":"杭州外企工人确诊 曾参加公司年会"},{"url":"https://so.toutiao.com/search?keyword=乘客被夹殒命+地铁如何担责","word":"乘客被夹殒命 地铁如何担责"},{"url":"https://so.toutiao.com/search?keyword=杭州一地划为中风险地区","word":"杭州一地划为中风险地区"},{"url":"https://so.toutiao.com/search?keyword=女子接触猴子后生病+症状类似新冠","word":"女子接触猴子后生病 症状类似新冠"},{"url":"https://so.toutiao.com/search?keyword=全国GDP第四城出炉","word":"全国GDP第四城出炉"},{"url":"https://so.toutiao.com/search?keyword=男孩疑被4只狗咬死+涉事狗系圈养","word":"男孩疑被4只狗咬死 涉事狗系圈养"},{"url":"https://so.toutiao.com/search?keyword=美光解散上海DRAM设计团队","word":"美光解散上海DRAM设计团队"},{"url":"https://so.toutiao.com/search?keyword=胡锡进：华盛顿恶毒导演外交官撤离","word":"胡锡进：华盛顿恶毒导演外交官撤离"},{"url":"https://so.toutiao.com/search?keyword=拜登：若俄入侵乌，将考虑制裁普京","word":"拜登：若俄入侵乌，将考虑制裁普京"},{"url":"https://so.toutiao.com/search?keyword=官员出轨下属妻子被杀+凶犯获无期","word":"官员出轨下属妻子被杀 凶犯获无期"},{"url":"https://so.toutiao.com/search?keyword=男子聚会假扮服务员给朋友惊喜","word":"男子聚会假扮服务员给朋友惊喜"},{"url":"https://so.toutiao.com/search?keyword=美国新任驻华大使宣誓就职","word":"美国新任驻华大使宣誓就职"},{"url":"https://so.toutiao.com/search?keyword=外交部：欢迎中亚五国元首出席冬奥","word":"外交部：欢迎中亚五国元首出席冬奥"},{"url":"https://so.toutiao.com/search?keyword=刘学州案反思：该如何追责网暴者","word":"刘学州案反思：该如何追责网暴者"},{"url":"https://so.toutiao.com/search?keyword=李霄鹏：阿兰来了心里就有底了","word":"李霄鹏：阿兰来了心里就有底了"},{"url":"https://so.toutiao.com/search?keyword=黄秀虹出任国美电器董事长","word":"黄秀虹出任国美电器董事长"},{"url":"https://so.toutiao.com/search?keyword=过年禁放鞭炮少了年味吗","word":"过年禁放鞭炮少了年味吗"},{"url":"https://so.toutiao.com/search?keyword=媒体评中国银行取消个人借记卡年费","word":"媒体评中国银行取消个人借记卡年费"},{"url":"https://so.toutiao.com/search?keyword=乌克兰抗议者试图冲击议会大楼","word":"乌克兰抗议者试图冲击议会大楼"},{"url":"https://so.toutiao.com/search?keyword=西安发布暴雪蓝色预警","word":"西安发布暴雪蓝色预警"},{"url":"https://so.toutiao.com/search?keyword=美军F-35C坠海对地区安全有何影响","word":"美军F-35C坠海对地区安全有何影响"},{"url":"https://so.toutiao.com/search?keyword=60岁东北大爷滑雪疯狂炫技","word":"60岁东北大爷滑雪疯狂炫技"},{"url":"https://so.toutiao.com/search?keyword=郑州2021年GDP公布：增长4.7％","word":"郑州2021年GDP公布：增长4.7％"},{"url":"https://so.toutiao.com/search?keyword=虎年将至中央3天开除5“虎”","word":"虎年将至中央3天开除5“虎”"},{"url":"https://so.toutiao.com/search?keyword=白百何晒与儿子合影","word":"白百何晒与儿子合影"},{"url":"https://so.toutiao.com/search?keyword=中方谈阿根廷总统将首次访华","word":"中方谈阿根廷总统将首次访华"},{"url":"https://so.toutiao.com/search?keyword=公安部发布《2021年全国姓名报告》","word":"公安部发布《2021年全国姓名报告》"},{"url":"https://so.toutiao.com/search?keyword=安徽雨雪持续+明天大别山区有暴雪","word":"安徽雨雪持续 明天大别山区有暴雪"},{"url":"https://so.toutiao.com/search?keyword=美军创记录派6架侦察机赴南海活动","word":"美军创记录派6架侦察机赴南海活动"},{"url":"https://so.toutiao.com/search?keyword=奥密克戎肆虐冲击美国就业市场","word":"奥密克戎肆虐冲击美国就业市场"},{"url":"https://so.toutiao.com/search?keyword=中国清零政策影响世界经济？中方回应","word":"中国清零政策影响世界经济？中方回应"},{"url":"https://so.toutiao.com/search?keyword=台扣押大陆船员+国台办：尽速放人","word":"台扣押大陆船员 国台办：尽速放人"},{"url":"https://so.toutiao.com/search?keyword=挪威研究：新冠2019年12月或已传播","word":"挪威研究：新冠2019年12月或已传播"},{"url":"https://so.toutiao.com/search?keyword=主持人蔡头去世","word":"主持人蔡头去世"},{"url":"https://so.toutiao.com/search?keyword=黑龙江2人从北京返回+隐瞒行程被拘","word":"黑龙江2人从北京返回 隐瞒行程被拘"},{"url":"https://so.toutiao.com/search?keyword=外媒曝立陶宛考虑要求台湾“改名”","word":"外媒曝立陶宛考虑要求台湾“改名”"},{"url":"https://so.toutiao.com/search?keyword=河北人大常委会原副主任谢计来被查","word":"河北人大常委会原副主任谢计来被查"},{"url":"https://so.toutiao.com/search?keyword=佩洛西宣布参加美2022年众议员选举","word":"佩洛西宣布参加美2022年众议员选举"},{"url":"https://so.toutiao.com/search?keyword=韦唯时隔8年复出为北京冬奥献唱","word":"韦唯时隔8年复出为北京冬奥献唱"},{"url":"https://so.toutiao.com/search?keyword=黑龙江肇东发现一例初筛阳性","word":"黑龙江肇东发现一例初筛阳性"},{"url":"https://so.toutiao.com/search?keyword=富祥药业近5个交易日累计跌幅达46%","word":"富祥药业近5个交易日累计跌幅达46%"},{"url":"https://so.toutiao.com/search?keyword=奥密克戎亚变体已在英感染400多例","word":"奥密克戎亚变体已在英感染400多例"},{"url":"https://so.toutiao.com/search?keyword=日本年度预算案再出错+首相致歉","word":"日本年度预算案再出错 首相致歉"},{"url":"https://so.toutiao.com/search?keyword=美政府警告：极端组织计划攻击电网","word":"美政府警告：极端组织计划攻击电网"},{"url":"https://so.toutiao.com/search?keyword=40余国及地区发现奥密克戎亚变种","word":"40余国及地区发现奥密克戎亚变种"},{"url":"https://so.toutiao.com/search?keyword=老人在养老院疑遭捆绑+警方立案","word":"老人在养老院疑遭捆绑 警方立案"},{"url":"https://so.toutiao.com/search?keyword=小伙回家相亲现场堪比大型海选","word":"小伙回家相亲现场堪比大型海选"},{"url":"https://so.toutiao.com/search?keyword=从北京西站返乡要隔离？各地要求不同","word":"从北京西站返乡要隔离？各地要求不同"},{"url":"https://so.toutiao.com/search?keyword=印度“比基尼小姐”参加选举惹争议","word":"印度“比基尼小姐”参加选举惹争议"},{"url":"https://so.toutiao.com/search?keyword=谭松韵央视网络春晚献唱《NewBoy》","word":"谭松韵央视网络春晚献唱《NewBoy》"},{"url":"https://so.toutiao.com/search?keyword=微信上线红包新玩法","word":"微信上线红包新玩法"},{"url":"https://so.toutiao.com/search?keyword=砂糖橘是什么梗","word":"砂糖橘是什么梗"},{"url":"https://so.toutiao.com/search?keyword=青岛姑娘带西安女孩回家过年","word":"青岛姑娘带西安女孩回家过年"},{"url":"https://so.toutiao.com/search?keyword=中日12强赛300国足球迷将进场助威","word":"中日12强赛300国足球迷将进场助威"},{"url":"https://so.toutiao.com/search?keyword=女子牛肉被盗谎称拌了老鼠药被拘","word":"女子牛肉被盗谎称拌了老鼠药被拘"},{"url":"https://so.toutiao.com/search?keyword=百位明星献唱一起向未来音乐短片","word":"百位明星献唱一起向未来音乐短片"},{"url":"https://so.toutiao.com/search?keyword=《开端》大结局烂尾了吗","word":"《开端》大结局烂尾了吗"},{"url":"https://so.toutiao.com/search?keyword=《开端》结局真相是什么","word":"《开端》结局真相是什么"},{"url":"https://so.toutiao.com/search?keyword=美国对芯片短缺发出警告","word":"美国对芯片短缺发出警告"},{"url":"https://so.toutiao.com/search?keyword=《一起向未来》录制现场欢乐场面","word":"《一起向未来》录制现场欢乐场面"},{"url":"https://so.toutiao.com/search?keyword=国台办：“湾湾”昵称感觉萌萌的","word":"国台办：“湾湾”昵称感觉萌萌的"},{"url":"https://so.toutiao.com/search?keyword=带星人能返乡吗？河南18地市出政策","word":"带星人能返乡吗？河南18地市出政策"},{"url":"https://so.toutiao.com/search?keyword=杭州新增1例本土确诊+感染奥密克戎","word":"杭州新增1例本土确诊 感染奥密克戎"},{"url":"https://so.toutiao.com/search?keyword=《新闻联播》正在直播","word":"《新闻联播》正在直播"},{"url":"https://so.toutiao.com/search?keyword=博物馆否认学生打碎文物价值130万","word":"博物馆否认学生打碎文物价值130万"},{"url":"https://so.toutiao.com/search?keyword=中纪委首提“斩断权力与资本勾连”","word":"中纪委首提“斩断权力与资本勾连”"},{"url":"https://so.toutiao.com/search?keyword=《黑神话：悟空》发布阶段成果","word":"《黑神话：悟空》发布阶段成果"},{"url":"https://so.toutiao.com/search?keyword=王永康任黑龙江省人大常委会副主任","word":"王永康任黑龙江省人大常委会副主任"},{"url":"https://so.toutiao.com/search?keyword=女子放下婴儿欲跳桥+外卖员一把拉回","word":"女子放下婴儿欲跳桥 外卖员一把拉回"},{"url":"https://so.toutiao.com/search?keyword=美国疫情地图几乎全境呈“红紫色”","word":"美国疫情地图几乎全境呈“红紫色”"},{"url":"https://so.toutiao.com/search?keyword=乌克兰议员称美供武器是上世纪垃圾","word":"乌克兰议员称美供武器是上世纪垃圾"},{"url":"https://so.toutiao.com/search?keyword=外交部：北约扩员是集团政治的体现","word":"外交部：北约扩员是集团政治的体现"},{"url":"https://so.toutiao.com/search?keyword=孙卓和姐姐孙悦开启互怼模式","word":"孙卓和姐姐孙悦开启互怼模式"},{"url":"https://so.toutiao.com/search?keyword=马斯克希望麦当劳接受狗狗币支付","word":"马斯克希望麦当劳接受狗狗币支付"},{"url":"https://so.toutiao.com/search?keyword=男孩失联3日+家属：被狗咬身亡","word":"男孩失联3日 家属：被狗咬身亡"},{"url":"https://so.toutiao.com/search?keyword=杭州现确诊+滨江实行“三区管理”","word":"杭州现确诊 滨江实行“三区管理”"},{"url":"https://so.toutiao.com/search?keyword=胸口疼是不是心脏病？","word":"胸口疼是不是心脏病？"},{"url":"https://so.toutiao.com/search?keyword=魔兽世界：绝版“幽灵虎”回归TBC","word":"魔兽世界：绝版“幽灵虎”回归TBC"},{"url":"https://so.toutiao.com/search?keyword=葛兰拟自购旗下2只在管医疗基金","word":"葛兰拟自购旗下2只在管医疗基金"},{"url":"https://so.toutiao.com/search?keyword=税务总局曝光5起涉税违法案件","word":"税务总局曝光5起涉税违法案件"},{"url":"https://so.toutiao.com/search?keyword=美军航母会因F35事故撤离南海吗","word":"美军航母会因F35事故撤离南海吗"},{"url":"https://so.toutiao.com/search?keyword=韩国两大总统候选人支持率差距拉大","word":"韩国两大总统候选人支持率差距拉大"},{"url":"https://so.toutiao.com/search?keyword=推倒性骚扰男子致其死亡属正当防卫","word":"推倒性骚扰男子致其死亡属正当防卫"},{"url":"https://so.toutiao.com/search?keyword=爱德华兹对阵开拓者砍下40分9板3断","word":"爱德华兹对阵开拓者砍下40分9板3断"},{"url":"https://so.toutiao.com/search?keyword=俄乌局势紧张+多国站队","word":"俄乌局势紧张 多国站队"},{"url":"https://so.toutiao.com/search?keyword=华为回应原智能驾驶总裁苏箐离职","word":"华为回应原智能驾驶总裁苏箐离职"},{"url":"https://so.toutiao.com/search?keyword=2022年省级两会重要人事任免","word":"2022年省级两会重要人事任免"},{"url":"https://so.toutiao.com/search?keyword=刘学州案：网络暴力者该如何处罚","word":"刘学州案：网络暴力者该如何处罚"},{"url":"https://so.toutiao.com/search?keyword=巴基斯坦首批中国产SH15加榴炮到货","word":"巴基斯坦首批中国产SH15加榴炮到货"},{"url":"https://so.toutiao.com/search?keyword=电影《龙马精神》定档","word":"电影《龙马精神》定档"},{"url":"https://so.toutiao.com/search?keyword=专家：美舰载机砸航母或有两原因","word":"专家：美舰载机砸航母或有两原因"},{"url":"https://so.toutiao.com/search?keyword=中央气象台发布今年首个暴雪蓝警","word":"中央气象台发布今年首个暴雪蓝警"},{"url":"https://so.toutiao.com/search?keyword=青岛航空客机拖移碾压1名机务致死","word":"青岛航空客机拖移碾压1名机务致死"},{"url":"https://so.toutiao.com/search?keyword=老师家访遇学生放羊硬塞400元","word":"老师家访遇学生放羊硬塞400元"},{"url":"https://so.toutiao.com/search?keyword=美国累计新冠死亡病例超87万例","word":"美国累计新冠死亡病例超87万例"},{"url":"https://so.toutiao.com/search?keyword=特斯拉皮卡量产版曝光","word":"特斯拉皮卡量产版曝光"},{"url":"https://so.toutiao.com/search?keyword=证券日报头版评论：挺起A股的脊梁","word":"证券日报头版评论：挺起A股的脊梁"},{"url":"https://so.toutiao.com/search?keyword=河北三河隔离点检出1例阳性","word":"河北三河隔离点检出1例阳性"},{"url":"https://so.toutiao.com/search?keyword=女子头痛呕吐系脑囊虫所致","word":"女子头痛呕吐系脑囊虫所致"},{"url":"https://so.toutiao.com/search?keyword=河北燕郊多个小区已封控","word":"河北燕郊多个小区已封控"},{"url":"https://so.toutiao.com/search?keyword=塔里木盆地新发现亿吨级油气区","word":"塔里木盆地新发现亿吨级油气区"},{"url":"https://so.toutiao.com/search?keyword=刘学州4个遗愿会有人帮他实现吗","word":"刘学州4个遗愿会有人帮他实现吗"},{"url":"https://so.toutiao.com/search?keyword=美谋划批准驻华使领馆“授权撤离”","word":"美谋划批准驻华使领馆“授权撤离”"},{"url":"https://so.toutiao.com/search?keyword=杭州新增1例本土确诊","word":"杭州新增1例本土确诊"},{"url":"https://so.toutiao.com/search?keyword=腾讯应届生怒怼领导过度加班","word":"腾讯应届生怒怼领导过度加班"},{"url":"https://so.toutiao.com/search?keyword=哈登谈在篮网不开心传闻：我没说","word":"哈登谈在篮网不开心传闻：我没说"},{"url":"https://so.toutiao.com/search?keyword=广西一厅官被开除党籍：代孕生子","word":"广西一厅官被开除党籍：代孕生子"},{"url":"https://so.toutiao.com/search?keyword=5岁小孩报警称捡到1岁小孩","word":"5岁小孩报警称捡到1岁小孩"},{"url":"https://so.toutiao.com/search?keyword=工信部：来电显示费未来将逐步取消","word":"工信部：来电显示费未来将逐步取消"},{"url":"https://so.toutiao.com/search?keyword=墨尔本一男子撞车引爆炸弹背心身亡","word":"墨尔本一男子撞车引爆炸弹背心身亡"},{"url":"https://so.toutiao.com/search?keyword=各国运动员备战冬奥有多拼","word":"各国运动员备战冬奥有多拼"},{"url":"https://so.toutiao.com/search?keyword=河南焦作一恒大项目快成烂尾楼","word":"河南焦作一恒大项目快成烂尾楼"},{"url":"https://so.toutiao.com/search?keyword=专家：歼-16D在电磁攻防领域优势大","word":"专家：歼-16D在电磁攻防领域优势大"},{"url":"https://so.toutiao.com/search?keyword=坚持不懈把全面从严治党向纵深推进","word":"坚持不懈把全面从严治党向纵深推进"},{"url":"https://so.toutiao.com/search?keyword=科比逝世两周年","word":"科比逝世两周年"},{"url":"https://so.toutiao.com/search?keyword=税务总局：对严重涉税违法行为严查","word":"税务总局：对严重涉税违法行为严查"},{"url":"https://so.toutiao.com/search?keyword=危机重重何去何从+五问乌克兰局势","word":"危机重重何去何从 五问乌克兰局势"},{"url":"https://so.toutiao.com/search?keyword=英国将取消完成疫苗接种者入境检测","word":"英国将取消完成疫苗接种者入境检测"},{"url":"https://so.toutiao.com/search?keyword=小年夜春晚众星惊艳瞬间","word":"小年夜春晚众星惊艳瞬间"},{"url":"https://so.toutiao.com/search?keyword=31省份新增24例本土确诊+涉7省市","word":"31省份新增24例本土确诊 涉7省市"},{"url":"https://so.toutiao.com/search?keyword=沉迷吃喝的“酒主任”倒了","word":"沉迷吃喝的“酒主任”倒了"},{"url":"https://so.toutiao.com/search?keyword=哈登战湖人砍33分12板11助2断1封盖","word":"哈登战湖人砍33分12板11助2断1封盖"},{"url":"https://so.toutiao.com/search?keyword=国家图书馆辟谣新东方捐赠精品课程","word":"国家图书馆辟谣新东方捐赠精品课程"},{"url":"https://so.toutiao.com/search?keyword=去年全国一般公共预算收入超20万亿","word":"去年全国一般公共预算收入超20万亿"},{"url":"https://so.toutiao.com/search?keyword=国台办：望立陶宛拿出行动纠正错误","word":"国台办：望立陶宛拿出行动纠正错误"},{"url":"https://so.toutiao.com/search?keyword=《黑神话：悟空》年终回顾","word":"《黑神话：悟空》年终回顾"},{"url":"https://so.toutiao.com/search?keyword=辽宁疾控：非必要不出辽不返辽","word":"辽宁疾控：非必要不出辽不返辽"},{"url":"https://so.toutiao.com/search?keyword=梁文博确诊新冠无缘德国大师赛","word":"梁文博确诊新冠无缘德国大师赛"},{"url":"https://so.toutiao.com/search?keyword=高中生出车祸昏迷+班主任将其喊醒","word":"高中生出车祸昏迷 班主任将其喊醒"},{"url":"https://so.toutiao.com/search?keyword=詹姆斯战篮网两分球13中12","word":"詹姆斯战篮网两分球13中12"},{"url":"https://so.toutiao.com/search?keyword=记者：哈登对欧文兼职打球感到困惑","word":"记者：哈登对欧文兼职打球感到困惑"},{"url":"https://so.toutiao.com/search?keyword=美国黑人运动员抵京受辱？信息有误","word":"美国黑人运动员抵京受辱？信息有误"},{"url":"https://so.toutiao.com/search?keyword=鸿海回应子公司年会重新抽奖","word":"鸿海回应子公司年会重新抽奖"},{"url":"https://so.toutiao.com/search?keyword=大学生返乡被家人安排住老屋隔离","word":"大学生返乡被家人安排住老屋隔离"},{"url":"https://so.toutiao.com/search?keyword=男子喜中500万+买彩票当晚被隔离","word":"男子喜中500万 买彩票当晚被隔离"},{"url":"https://so.toutiao.com/search?keyword=开端剧组到底寄给赵今麦多少面锦旗","word":"开端剧组到底寄给赵今麦多少面锦旗"},{"url":"https://so.toutiao.com/search?keyword=王晶谈新版《倚天屠龙记》","word":"王晶谈新版《倚天屠龙记》"},{"url":"https://so.toutiao.com/search?keyword=中国台北代表团17人报名参加冬奥会","word":"中国台北代表团17人报名参加冬奥会"},{"url":"https://so.toutiao.com/search?keyword=警方：男子因借款纠纷刺伤360员工","word":"警方：男子因借款纠纷刺伤360员工"},{"url":"https://so.toutiao.com/search?keyword=肯纳德3+1绝杀奇才导演35分逆转","word":"肯纳德3+1绝杀奇才导演35分逆转"},{"url":"https://so.toutiao.com/search?keyword=美军证实事故F-35C坠入南海","word":"美军证实事故F-35C坠入南海"},{"url":"https://so.toutiao.com/search?keyword=女子称被民警打4耳光+警方：无监控","word":"女子称被民警打4耳光 警方：无监控"},{"url":"https://so.toutiao.com/search?keyword=学生摔碎博物馆百万文物？馆方回应","word":"学生摔碎博物馆百万文物？馆方回应"},{"url":"https://so.toutiao.com/search?keyword=广西多名山区临时教师被淘汰","word":"广西多名山区临时教师被淘汰"},{"url":"https://so.toutiao.com/search?keyword=深圳放宽市场准入特别措施发布","word":"深圳放宽市场准入特别措施发布"},{"url":"https://so.toutiao.com/search?keyword=国开行原副行长何兴祥被双开","word":"国开行原副行长何兴祥被双开"},{"url":"https://so.toutiao.com/search?keyword=恩比德42+14+4盖帽+76人击败鹈鹕","word":"恩比德42+14+4盖帽 76人击败鹈鹕"},{"url":"https://so.toutiao.com/search?keyword=穆雷19+10+马刺30分大胜火箭","word":"穆雷19+10 马刺30分大胜火箭"},{"url":"https://so.toutiao.com/search?keyword=浓眉复出詹姆斯33分+湖人胜篮网","word":"浓眉复出詹姆斯33分 湖人胜篮网"},{"url":"https://so.toutiao.com/search?keyword=考辛斯战活塞14分钟5投1中6次失误","word":"考辛斯战活塞14分钟5投1中6次失误"},{"url":"https://so.toutiao.com/search?keyword=纳什谈哈登交易流言：不确定真实性","word":"纳什谈哈登交易流言：不确定真实性"},{"url":"https://so.toutiao.com/search?keyword=曝哈登有意离开篮网","word":"曝哈登有意离开篮网"},{"url":"https://so.toutiao.com/search?keyword=法总统候选人呼吁法国退出北约","word":"法总统候选人呼吁法国退出北约"},{"url":"https://so.toutiao.com/search?keyword=通过春晚走红的港台明星","word":"通过春晚走红的港台明星"},{"url":"https://so.toutiao.com/search?keyword=打工人返乡过年破防瞬间","word":"打工人返乡过年破防瞬间"},{"url":"https://so.toutiao.com/search?keyword=疾控人回忆战疫2年：4省奔波聚少离多","word":"疾控人回忆战疫2年：4省奔波聚少离多"},{"url":"https://so.toutiao.com/search?keyword=市政协原副主席被开党籍：代孕生子","word":"市政协原副主席被开党籍：代孕生子"},{"url":"https://so.toutiao.com/search?keyword=钟丽缇晒与俩女儿温馨互动视频","word":"钟丽缇晒与俩女儿温馨互动视频"},{"url":"https://so.toutiao.com/search?keyword=世卫官员：欧洲可能正接近结束疫情","word":"世卫官员：欧洲可能正接近结束疫情"},{"url":"https://so.toutiao.com/search?keyword=北京昨增14例本土确诊5例无症状","word":"北京昨增14例本土确诊5例无症状"},{"url":"https://so.toutiao.com/search?keyword=央企抄底“全国地王”","word":"央企抄底“全国地王”"},{"url":"https://so.toutiao.com/search?keyword=4个象群32头野象现身野象谷","word":"4个象群32头野象现身野象谷"},{"url":"https://so.toutiao.com/search?keyword=保定新增1例确诊+从北京丰台返乡","word":"保定新增1例确诊 从北京丰台返乡"},{"url":"https://so.toutiao.com/search?keyword=白敬亭赵今麦吻戏","word":"白敬亭赵今麦吻戏"},{"url":"https://so.toutiao.com/search?keyword=立陶宛将向乌克兰转让毒刺防空导弹","word":"立陶宛将向乌克兰转让毒刺防空导弹"},{"url":"https://so.toutiao.com/search?keyword=朋友圈的年货PK有多拼","word":"朋友圈的年货PK有多拼"},{"url":"https://so.toutiao.com/search?keyword=河南国风小年夜晚会","word":"河南国风小年夜晚会"},{"url":"https://so.toutiao.com/search?keyword=湖北省委巡视组原组长靳祖春被双开","word":"湖北省委巡视组原组长靳祖春被双开"},{"url":"https://so.toutiao.com/search?keyword=王姬晒北京街头散步视频","word":"王姬晒北京街头散步视频"},{"url":"https://so.toutiao.com/search?keyword=孙悦辟谣孙卓英语差","word":"孙悦辟谣孙卓英语差"},{"url":"https://so.toutiao.com/search?keyword=主持天团重新解说08年奥运开幕式","word":"主持天团重新解说08年奥运开幕式"},{"url":"https://so.toutiao.com/search?keyword=2021年我国财政收入突破20万亿元","word":"2021年我国财政收入突破20万亿元"},{"url":"https://so.toutiao.com/search?keyword=中国空天发动机首战圆满成功","word":"中国空天发动机首战圆满成功"},{"url":"https://so.toutiao.com/search?keyword=年底讨薪人：担心离开工地要不回钱","word":"年底讨薪人：担心离开工地要不回钱"},{"url":"https://so.toutiao.com/search?keyword=王冰冰唱的《想去海边》好甜","word":"王冰冰唱的《想去海边》好甜"},{"url":"https://so.toutiao.com/search?keyword=奶爸助力冬奥+带娃耗时7天造冰屋","word":"奶爸助力冬奥 带娃耗时7天造冰屋"},{"url":"https://so.toutiao.com/search?keyword=男童扔鞭炮炸飞5个井盖+母亲受伤","word":"男童扔鞭炮炸飞5个井盖 母亲受伤"},{"url":"https://so.toutiao.com/search?keyword=谭德塞锁定世卫总干事第二任期","word":"谭德塞锁定世卫总干事第二任期"},{"url":"https://so.toutiao.com/search?keyword=民警捡到撕碎的抚养委托书","word":"民警捡到撕碎的抚养委托书"},{"url":"https://so.toutiao.com/search?keyword=百亿身家女富豪朱林瑶被立案调查","word":"百亿身家女富豪朱林瑶被立案调查"},{"url":"https://so.toutiao.com/search?keyword=姆巴佩：阿什拉夫是世界最佳右后卫","word":"姆巴佩：阿什拉夫是世界最佳右后卫"},{"url":"https://so.toutiao.com/search?keyword=歌手张宇将重返歌坛","word":"歌手张宇将重返歌坛"},{"url":"https://so.toutiao.com/search?keyword=俄南部军区六千士兵进行战备检查","word":"俄南部军区六千士兵进行战备检查"},{"url":"https://so.toutiao.com/search?keyword=俄罗斯将派超500人参加北京冬奥会","word":"俄罗斯将派超500人参加北京冬奥会"},{"url":"https://so.toutiao.com/search?keyword=两家同一天办满月酒互相较劲","word":"两家同一天办满月酒互相较劲"},{"url":"https://so.toutiao.com/search?keyword=赵龙任福建省长+成全国最年轻省长","word":"赵龙任福建省长 成全国最年轻省长"},{"url":"https://so.toutiao.com/search?keyword=华裔教授陈刚就“间谍案”首次发声","word":"华裔教授陈刚就“间谍案”首次发声"},{"url":"https://so.toutiao.com/search?keyword=只是想回家过年+怎么这么难","word":"只是想回家过年 怎么这么难"},{"url":"https://so.toutiao.com/search?keyword=腾讯视频制片人张萌被移送公安","word":"腾讯视频制片人张萌被移送公安"},{"url":"https://so.toutiao.com/search?keyword=非洲小伙中国城买年货开心爆棚","word":"非洲小伙中国城买年货开心爆棚"},{"url":"https://so.toutiao.com/search?keyword=日本女演员深田恭子确诊新冠","word":"日本女演员深田恭子确诊新冠"},{"url":"https://so.toutiao.com/search?keyword=31省GDP数据出炉+11地增速跑赢全国","word":"31省GDP数据出炉 11地增速跑赢全国"},{"url":"https://so.toutiao.com/search?keyword=春节临近+持币过节还是持股过节","word":"春节临近 持币过节还是持股过节"},{"url":"https://so.toutiao.com/search?keyword=天津昨日零新增","word":"天津昨日零新增"},{"url":"https://so.toutiao.com/search?keyword=日本超七成地区将进入准紧急状态","word":"日本超七成地区将进入准紧急状态"},{"url":"https://so.toutiao.com/search?keyword=海南过去两年GDP平均增速全国居首","word":"海南过去两年GDP平均增速全国居首"},{"url":"https://so.toutiao.com/search?keyword=张同学小年炸年货看馋了","word":"张同学小年炸年货看馋了"},{"url":"https://so.toutiao.com/search?keyword=我国成功发射L-SAR+01组A星","word":"我国成功发射L-SAR 01组A星"},{"url":"https://so.toutiao.com/search?keyword=《小虎墩大英雄》教会了孩子什么","word":"《小虎墩大英雄》教会了孩子什么"},{"url":"https://so.toutiao.com/search?keyword=2021年广州地区生产总值2.82万亿元","word":"2021年广州地区生产总值2.82万亿元"},{"url":"https://so.toutiao.com/search?keyword=美股剧烈震荡+道指再现千点反弹","word":"美股剧烈震荡 道指再现千点反弹"},{"url":"https://so.toutiao.com/search?keyword=特大暴雪预报已现+南方会遇雪灾吗","word":"特大暴雪预报已现 南方会遇雪灾吗"},{"url":"https://so.toutiao.com/search?keyword=济南一市场多个样本初筛阳性","word":"济南一市场多个样本初筛阳性"},{"url":"https://so.toutiao.com/search?keyword=中国银行下月起取消个人借记卡年费","word":"中国银行下月起取消个人借记卡年费"},{"url":"https://so.toutiao.com/search?keyword=全球日增确诊超398万例","word":"全球日增确诊超398万例"},{"url":"https://so.toutiao.com/search?keyword=炒热乌克兰局势+美国在盘算什么","word":"炒热乌克兰局势 美国在盘算什么"},{"url":"https://so.toutiao.com/search?keyword=俄乌危机将如何影响全球资本市场","word":"俄乌危机将如何影响全球资本市场"},{"url":"https://so.toutiao.com/search?keyword=分析师：外围风险对A股冲击近尾声","word":"分析师：外围风险对A股冲击近尾声"},{"url":"https://so.toutiao.com/search?keyword=曝沃尔不接受任何放弃金钱的买断","word":"曝沃尔不接受任何放弃金钱的买断"},{"url":"https://so.toutiao.com/search?keyword=62岁白发奶奶：从病床走上T台","word":"62岁白发奶奶：从病床走上T台"},{"url":"https://so.toutiao.com/search?keyword=奶奶做一床豆沙包被孩子压成薄饼","word":"奶奶做一床豆沙包被孩子压成薄饼"},{"url":"https://so.toutiao.com/search?keyword=天津蓟州区多家景区恢复营业","word":"天津蓟州区多家景区恢复营业"},{"url":"https://so.toutiao.com/search?keyword=看《开端》的后遗症","word":"看《开端》的后遗症"},{"url":"https://so.toutiao.com/search?keyword=郑州部分区域今起解封","word":"郑州部分区域今起解封"},{"url":"https://so.toutiao.com/search?keyword=券商整体降薪30%传言沸沸扬扬","word":"券商整体降薪30%传言沸沸扬扬"},{"url":"https://so.toutiao.com/search?keyword=韩国总统候选人再行“跪拜大礼”","word":"韩国总统候选人再行“跪拜大礼”"},{"url":"https://so.toutiao.com/search?keyword=俄罗斯波罗的海舰队举行军事演习","word":"俄罗斯波罗的海舰队举行军事演习"},{"url":"https://so.toutiao.com/search?keyword=自研新冠口服药预计下半年进入临床","word":"自研新冠口服药预计下半年进入临床"},{"url":"https://so.toutiao.com/search?keyword=美国会招标研究解放军征兵信息","word":"美国会招标研究解放军征兵信息"},{"url":"https://so.toutiao.com/search?keyword=多家相关上市公司回应俄乌紧张局势","word":"多家相关上市公司回应俄乌紧张局势"},{"url":"https://so.toutiao.com/search?keyword=曝巴萨已与凯西就加盟进行深入交谈","word":"曝巴萨已与凯西就加盟进行深入交谈"},{"url":"https://so.toutiao.com/search?keyword=美舰载机在南海坠毁致7人受伤","word":"美舰载机在南海坠毁致7人受伤"},{"url":"https://so.toutiao.com/search?keyword=北京天安门广场升旗仪式正直播","word":"北京天安门广场升旗仪式正直播"},{"url":"https://so.toutiao.com/search?keyword=女模特每月10万养混血三胞胎","word":"女模特每月10万养混血三胞胎"},{"url":"https://so.toutiao.com/search?keyword=北京新增本土12+3+丰台2地升中风险","word":"北京新增本土12+3 丰台2地升中风险"},{"url":"https://so.toutiao.com/search?keyword=油价或迎来今年第三次上调","word":"油价或迎来今年第三次上调"},{"url":"https://so.toutiao.com/search?keyword=杭州杀妻碎尸案二审+凶手要求无罪","word":"杭州杀妻碎尸案二审 凶手要求无罪"},{"url":"https://so.toutiao.com/search?keyword=绥芬河和东宁共发现阳性感染者13人","word":"绥芬河和东宁共发现阳性感染者13人"},{"url":"https://so.toutiao.com/search?keyword=歼16-D电子战机首现台海意味着什么","word":"歼16-D电子战机首现台海意味着什么"},{"url":"https://so.toutiao.com/search?keyword=老人手持钢架拦婚车要红包","word":"老人手持钢架拦婚车要红包"},{"url":"https://so.toutiao.com/search?keyword=29岁姑娘做了11年中老年模特","word":"29岁姑娘做了11年中老年模特"},{"url":"https://so.toutiao.com/search?keyword=公安部成立小组肃清孙力军团伙流毒","word":"公安部成立小组肃清孙力军团伙流毒"},{"url":"https://so.toutiao.com/search?keyword=女乘客被夹身亡+上海地铁：配合调查","word":"女乘客被夹身亡 上海地铁：配合调查"},{"url":"https://so.toutiao.com/search?keyword=老两口已故独子存款已找到+仅3元","word":"老两口已故独子存款已找到 仅3元"},{"url":"https://so.toutiao.com/search?keyword=立陶宛将派代表团参加北京冬奥会","word":"立陶宛将派代表团参加北京冬奥会"},{"url":"https://so.toutiao.com/search?keyword=俄罗斯东部军区军队将陆续前往白俄","word":"俄罗斯东部军区军队将陆续前往白俄"},{"url":"https://so.toutiao.com/search?keyword=主动投案的女官员被指毫无政治定力","word":"主动投案的女官员被指毫无政治定力"},{"url":"https://so.toutiao.com/search?keyword=网信办：严防违法失德艺人转移阵地","word":"网信办：严防违法失德艺人转移阵地"},{"url":"https://so.toutiao.com/search?keyword=央视春晚第三次大联排","word":"央视春晚第三次大联排"},{"url":"https://so.toutiao.com/search?keyword=《乡村爱情14》还有谢大脚","word":"《乡村爱情14》还有谢大脚"},{"url":"https://so.toutiao.com/search?keyword=庞建国告别式在台北第一殡仪馆举行","word":"庞建国告别式在台北第一殡仪馆举行"},{"url":"https://so.toutiao.com/search?keyword=河北人大原副主任宋太平被逮捕","word":"河北人大原副主任宋太平被逮捕"},{"url":"https://so.toutiao.com/search?keyword=深圳GDP超3万亿+或进世界前30名","word":"深圳GDP超3万亿 或进世界前30名"},{"url":"https://so.toutiao.com/search?keyword=电视剧《人世间》定档","word":"电视剧《人世间》定档"},{"url":"https://so.toutiao.com/search?keyword=上海最惨购房人：估算损失近千万","word":"上海最惨购房人：估算损失近千万"},{"url":"https://so.toutiao.com/search?keyword=《欢乐颂3》正式杀青","word":"《欢乐颂3》正式杀青"},{"url":"https://so.toutiao.com/search?keyword=云南一官员被双开：致抗疫物资闲置","word":"云南一官员被双开：致抗疫物资闲置"},{"url":"https://so.toutiao.com/search?keyword=南京遇害女大学生父亲要求庭审直播","word":"南京遇害女大学生父亲要求庭审直播"},{"url":"https://so.toutiao.com/search?keyword=2022山东春晚节目单发布","word":"2022山东春晚节目单发布"},{"url":"https://so.toutiao.com/search?keyword=乌克兰回应美撤离驻乌使馆人员","word":"乌克兰回应美撤离驻乌使馆人员"},{"url":"https://so.toutiao.com/search?keyword=女子上班一个月还要倒贴600多","word":"女子上班一个月还要倒贴600多"},{"url":"https://so.toutiao.com/search?keyword=美国或向东欧增派8500名士兵","word":"美国或向东欧增派8500名士兵"},{"url":"https://so.toutiao.com/search?keyword=成品油调价窗口将于1月29日开启","word":"成品油调价窗口将于1月29日开启"},{"url":"https://so.toutiao.com/search?keyword=在美留学生买5张机票仍难回国","word":"在美留学生买5张机票仍难回国"},{"url":"https://so.toutiao.com/search?keyword=拜登致电记者就爆粗口道歉","word":"拜登致电记者就爆粗口道歉"},{"url":"https://so.toutiao.com/search?keyword=孙海洋一家回湖北老家过年","word":"孙海洋一家回湖北老家过年"},{"url":"https://so.toutiao.com/search?keyword=哈萨克斯坦等中亚三国遇大规模断电","word":"哈萨克斯坦等中亚三国遇大规模断电"},{"url":"https://so.toutiao.com/search?keyword=20家基金公司解读A股大跌原因","word":"20家基金公司解读A股大跌原因"},{"url":"https://so.toutiao.com/search?keyword=欧美领导人举行乌克兰“重大会议”","word":"欧美领导人举行乌克兰“重大会议”"},{"url":"https://so.toutiao.com/search?keyword=三个国家恢复在联合国大会投票权","word":"三个国家恢复在联合国大会投票权"},{"url":"https://so.toutiao.com/search?keyword=妈妈为女儿织近百件时尚毛衣","word":"妈妈为女儿织近百件时尚毛衣"},{"url":"https://so.toutiao.com/search?keyword=住建部：大力发展装配式建筑","word":"住建部：大力发展装配式建筑"},{"url":"https://so.toutiao.com/search?keyword=中国造护卫舰入列巴基斯坦海军","word":"中国造护卫舰入列巴基斯坦海军"},{"url":"https://so.toutiao.com/search?keyword=河南夫妇上演现实版你是我的眼","word":"河南夫妇上演现实版你是我的眼"},{"url":"https://so.toutiao.com/search?keyword=北青报：国足战日本或用三中卫体系","word":"北青报：国足战日本或用三中卫体系"},{"url":"https://so.toutiao.com/search?keyword=《长津湖之水门桥》导演仅徐克一人","word":"《长津湖之水门桥》导演仅徐克一人"},{"url":"https://so.toutiao.com/search?keyword=张杰公司被拖欠千万演唱会款项","word":"张杰公司被拖欠千万演唱会款项"},{"url":"https://so.toutiao.com/search?keyword=沪指创一年半以来最大单日跌幅","word":"沪指创一年半以来最大单日跌幅"},{"url":"https://so.toutiao.com/search?keyword=男子刚要回2年6万工钱又不慎丢失","word":"男子刚要回2年6万工钱又不慎丢失"},{"url":"https://so.toutiao.com/search?keyword=央视2022网络春晚","word":"央视2022网络春晚"},{"url":"https://so.toutiao.com/search?keyword=谢娜自曝生二胎患产后抑郁","word":"谢娜自曝生二胎患产后抑郁"}]