[{"url":"https://so.toutiao.com/search?keyword=日本首相APEC上玩手机坐着握手挨批","word":"日本首相APEC上玩手机坐着握手挨批"},{"url":"https://so.toutiao.com/search?keyword=百雀羚涉嫌添加禁用原料基本属实","word":"百雀羚涉嫌添加禁用原料基本属实"},{"url":"https://so.toutiao.com/search?keyword=中国实践推动全球人工智能安全发展","word":"中国实践推动全球人工智能安全发展"},{"url":"https://so.toutiao.com/search?keyword=人民日报点赞国足","word":"人民日报点赞国足"},{"url":"https://so.toutiao.com/search?keyword=鱼被遗忘1年饿得只剩骨架","word":"鱼被遗忘1年饿得只剩骨架"},{"url":"https://so.toutiao.com/search?keyword=广东东莞市委原书记徐建华被查","word":"广东东莞市委原书记徐建华被查"},{"url":"https://so.toutiao.com/search?keyword=国足小组垫底但距第二只差1分","word":"国足小组垫底但距第二只差1分"},{"url":"https://so.toutiao.com/search?keyword=合肥房姐李梅83套房拍卖结束","word":"合肥房姐李梅83套房拍卖结束"},{"url":"https://so.toutiao.com/search?keyword=G20峰会上的减贫“中国方案”","word":"G20峰会上的减贫“中国方案”"},{"url":"https://so.toutiao.com/search?keyword=国足所在小组彻底乱了","word":"国足所在小组彻底乱了"},{"url":"https://so.toutiao.com/search?keyword=广州车展实拍五菱缤果SUV唐老鸭版","word":"广州车展实拍五菱缤果SUV唐老鸭版"},{"url":"https://so.toutiao.com/search?keyword=耿爽当面反击美国代表","word":"耿爽当面反击美国代表"},{"url":"https://so.toutiao.com/search?keyword=久保建英赞国足：反击比欧洲队还快","word":"久保建英赞国足：反击比欧洲队还快"},{"url":"https://so.toutiao.com/search?keyword=余承东全网首曝Mate70","word":"余承东全网首曝Mate70"},{"url":"https://so.toutiao.com/search?keyword=学校辟谣家长开直升机接孩子","word":"学校辟谣家长开直升机接孩子"},{"url":"https://so.toutiao.com/search?keyword=范志毅吸氧观赛中日大战","word":"范志毅吸氧观赛中日大战"},{"url":"https://so.toutiao.com/search?keyword=良品铺子被举报冤不冤","word":"良品铺子被举报冤不冤"},{"url":"https://so.toutiao.com/search?keyword=“猴哥”在洛阳老君山被困八卦炉","word":"“猴哥”在洛阳老君山被困八卦炉"},{"url":"https://so.toutiao.com/search?keyword=伊万赛后表情惆怅记者集体送上掌声","word":"伊万赛后表情惆怅记者集体送上掌声"},{"url":"https://so.toutiao.com/search?keyword=心肌梗死的10个高危时刻","word":"心肌梗死的10个高危时刻"},{"url":"https://so.toutiao.com/search?keyword=市民质疑城管无证执法被怼","word":"市民质疑城管无证执法被怼"},{"url":"https://so.toutiao.com/search?keyword=美公司推4年旅行套餐躲特朗普任期","word":"美公司推4年旅行套餐躲特朗普任期"},{"url":"https://so.toutiao.com/search?keyword=飞猪回应夫妻去南极想睡一间房被拒","word":"飞猪回应夫妻去南极想睡一间房被拒"},{"url":"https://so.toutiao.com/search?keyword=为什么心脏问题会反射到胃","word":"为什么心脏问题会反射到胃"},{"url":"https://so.toutiao.com/search?keyword=男生拿校园卡逗喜鹊下一秒被叼走","word":"男生拿校园卡逗喜鹊下一秒被叼走"},{"url":"https://so.toutiao.com/search?keyword=大妈头顶水管刷盘子效率加倍","word":"大妈头顶水管刷盘子效率加倍"},{"url":"https://so.toutiao.com/search?keyword=心梗发作5个预警信号","word":"心梗发作5个预警信号"},{"url":"https://so.toutiao.com/search?keyword=大V：国足踢出了希望","word":"大V：国足踢出了希望"},{"url":"https://so.toutiao.com/search?keyword=租户把民宅当猫舍%20邻居：气味扑鼻","word":"租户把民宅当猫舍 邻居：气味扑鼻"},{"url":"https://so.toutiao.com/search?keyword=俄专家：俄或摧毁基辅决策中心","word":"俄专家：俄或摧毁基辅决策中心"},{"url":"https://so.toutiao.com/search?keyword=钟睒睒：当前社会对商人提太多要求","word":"钟睒睒：当前社会对商人提太多要求"},{"url":"https://so.toutiao.com/search?keyword=国足1-3日本！近5年首破日本队球门","word":"国足1-3日本！近5年首破日本队球门"},{"url":"https://so.toutiao.com/search?keyword=双胞胎宝宝长得“两模两样”","word":"双胞胎宝宝长得“两模两样”"},{"url":"https://so.toutiao.com/search?keyword=参演官兵坐运-20抵达巴基斯坦","word":"参演官兵坐运-20抵达巴基斯坦"},{"url":"https://so.toutiao.com/search?keyword=粉丝面画国旗为国足加油助威","word":"粉丝面画国旗为国足加油助威"},{"url":"https://so.toutiao.com/search?keyword=宝宝睡觉把脚丫架爸爸脖子上","word":"宝宝睡觉把脚丫架爸爸脖子上"},{"url":"https://so.toutiao.com/search?keyword=民族政策大改%20新西兰人连续9天抗议","word":"民族政策大改 新西兰人连续9天抗议"},{"url":"https://so.toutiao.com/search?keyword=日本队最快下轮锁定世界杯资格","word":"日本队最快下轮锁定世界杯资格"},{"url":"https://so.toutiao.com/search?keyword=无人机找到疑似咬伤人东北虎热源","word":"无人机找到疑似咬伤人东北虎热源"},{"url":"https://so.toutiao.com/search?keyword=吴静任湖北省财政厅党组书记","word":"吴静任湖北省财政厅党组书记"},{"url":"https://so.toutiao.com/search?keyword=日本队长：现在展现的只是最低水平","word":"日本队长：现在展现的只是最低水平"},{"url":"https://so.toutiao.com/search?keyword=有人砸60多万元“抄底”黄金","word":"有人砸60多万元“抄底”黄金"},{"url":"https://so.toutiao.com/search?keyword=日本展出新型激光武器性能如何","word":"日本展出新型激光武器性能如何"},{"url":"https://so.toutiao.com/search?keyword=男子酒驾还暴力袭警被采取强制措施","word":"男子酒驾还暴力袭警被采取强制措施"},{"url":"https://so.toutiao.com/search?keyword=女生分享学习经验意外爆出自己的瓜","word":"女生分享学习经验意外爆出自己的瓜"},{"url":"https://so.toutiao.com/search?keyword=国际贵金属期货普遍收涨","word":"国际贵金属期货普遍收涨"},{"url":"https://so.toutiao.com/search?keyword=张纪中四胎女儿迎来满月","word":"张纪中四胎女儿迎来满月"},{"url":"https://so.toutiao.com/search?keyword=《白夜破晓》今日开播","word":"《白夜破晓》今日开播"},{"url":"https://so.toutiao.com/search?keyword=小伙当面向雷军投简历","word":"小伙当面向雷军投简历"},{"url":"https://so.toutiao.com/search?keyword=珠海航展疑现“背包间谍男”","word":"珠海航展疑现“背包间谍男”"},{"url":"https://so.toutiao.com/search?keyword=日本主帅回应中国球迷嘘日本国歌","word":"日本主帅回应中国球迷嘘日本国歌"},{"url":"https://so.toutiao.com/search?keyword=华为Mate70已到店","word":"华为Mate70已到店"},{"url":"https://so.toutiao.com/search?keyword=珠海航展有哪些遗憾","word":"珠海航展有哪些遗憾"},{"url":"https://so.toutiao.com/search?keyword=人民日报评国足：无惧强敌赢得尊重","word":"人民日报评国足：无惧强敌赢得尊重"},{"url":"https://so.toutiao.com/search?keyword=目击者：大牯牛山纵火者不听劝阻","word":"目击者：大牯牛山纵火者不听劝阻"},{"url":"https://so.toutiao.com/search?keyword=市民质疑城管无证执法被怼%20官方回应","word":"市民质疑城管无证执法被怼 官方回应"},{"url":"https://so.toutiao.com/search?keyword=小伙称做演唱会手机出租每场赚几千","word":"小伙称做演唱会手机出租每场赚几千"},{"url":"https://so.toutiao.com/search?keyword=中国巴基斯坦联合演练反恐有何深意","word":"中国巴基斯坦联合演练反恐有何深意"},{"url":"https://so.toutiao.com/search?keyword=G20峰会拍“全家福”拜登来晚了","word":"G20峰会拍“全家福”拜登来晚了"},{"url":"https://so.toutiao.com/search?keyword=乌首次用美陆军战术导弹系统袭击俄","word":"乌首次用美陆军战术导弹系统袭击俄"},{"url":"https://so.toutiao.com/search?keyword=拜登下榻酒店对面轮播中企广告","word":"拜登下榻酒店对面轮播中企广告"},{"url":"https://so.toutiao.com/search?keyword=申通：10月快递业务收入增长24.86%","word":"申通：10月快递业务收入增长24.86%"},{"url":"https://so.toutiao.com/search?keyword=学校给卫生差的寝室颁发流动紫旗","word":"学校给卫生差的寝室颁发流动紫旗"},{"url":"https://so.toutiao.com/search?keyword=邓炳强谈戴耀廷等乱港分子获刑","word":"邓炳强谈戴耀廷等乱港分子获刑"},{"url":"https://so.toutiao.com/search?keyword=印尼2-0胜沙特%20反超国足排小组第三","word":"印尼2-0胜沙特 反超国足排小组第三"},{"url":"https://so.toutiao.com/search?keyword=钟睒睒：我永远不会做直播带货","word":"钟睒睒：我永远不会做直播带货"},{"url":"https://so.toutiao.com/search?keyword=乌称幼师首次实战就打下导弹引质疑","word":"乌称幼师首次实战就打下导弹引质疑"},{"url":"https://so.toutiao.com/search?keyword=顾晓东任苏州张家港市代理市长","word":"顾晓东任苏州张家港市代理市长"},{"url":"https://so.toutiao.com/search?keyword=挑担比赛证明了姜还是老的辣","word":"挑担比赛证明了姜还是老的辣"},{"url":"https://so.toutiao.com/search?keyword=杉杉股份创始人遗孀上任董事长","word":"杉杉股份创始人遗孀上任董事长"},{"url":"https://so.toutiao.com/search?keyword=东北虎为何进村对人发起攻击","word":"东北虎为何进村对人发起攻击"},{"url":"https://so.toutiao.com/search?keyword=广东沿海多地海水倒灌%20车辆被淹","word":"广东沿海多地海水倒灌 车辆被淹"},{"url":"https://so.toutiao.com/search?keyword=国足在《歌唱祖国》中告别2024","word":"国足在《歌唱祖国》中告别2024"},{"url":"https://so.toutiao.com/search?keyword=网红打假遇“硬茬”%20良品铺子起诉","word":"网红打假遇“硬茬” 良品铺子起诉"},{"url":"https://so.toutiao.com/search?keyword=“拉萨职工均可申请租房提取”不实","word":"“拉萨职工均可申请租房提取”不实"},{"url":"https://so.toutiao.com/search?keyword=17岁女孩查出宫颈癌已是晚期","word":"17岁女孩查出宫颈癌已是晚期"},{"url":"https://so.toutiao.com/search?keyword=反中乱港分子黄之锋被判囚56个月","word":"反中乱港分子黄之锋被判囚56个月"},{"url":"https://so.toutiao.com/search?keyword=李子柒称不希望青少年梦想当网红","word":"李子柒称不希望青少年梦想当网红"},{"url":"https://so.toutiao.com/search?keyword=中日大战国足进步明显","word":"中日大战国足进步明显"},{"url":"https://so.toutiao.com/search?keyword=小米车展定制矿泉水被卖到132元2瓶","word":"小米车展定制矿泉水被卖到132元2瓶"},{"url":"https://so.toutiao.com/search?keyword=谷歌聊天机器人竟回复称人类去死吧","word":"谷歌聊天机器人竟回复称人类去死吧"},{"url":"https://so.toutiao.com/search?keyword=小米交出史上最强业绩","word":"小米交出史上最强业绩"},{"url":"https://so.toutiao.com/search?keyword=特朗普拟构建完全自动驾驶汽车框架","word":"特朗普拟构建完全自动驾驶汽车框架"},{"url":"https://so.toutiao.com/search?keyword=军事专家：白宫在给普京下套","word":"军事专家：白宫在给普京下套"},{"url":"https://so.toutiao.com/search?keyword=乱港分子戴耀廷被判10年","word":"乱港分子戴耀廷被判10年"},{"url":"https://so.toutiao.com/search?keyword=所有美航母已离开中东","word":"所有美航母已离开中东"},{"url":"https://so.toutiao.com/search?keyword=李庚希拿金鸡影后为何争议这么大","word":"李庚希拿金鸡影后为何争议这么大"},{"url":"https://so.toutiao.com/search?keyword=麦琳引发的熏鸡事变被全网围剿","word":"麦琳引发的熏鸡事变被全网围剿"},{"url":"https://so.toutiao.com/search?keyword=张咪自曝第三次患癌","word":"张咪自曝第三次患癌"},{"url":"https://so.toutiao.com/search?keyword=官方通报“报警人被关留置室”","word":"官方通报“报警人被关留置室”"},{"url":"https://so.toutiao.com/search?keyword=姐姐送房给弟弟住被1400万卖了","word":"姐姐送房给弟弟住被1400万卖了"},{"url":"https://so.toutiao.com/search?keyword=“深圳八景”之中英街遭遇海水倒灌","word":"“深圳八景”之中英街遭遇海水倒灌"},{"url":"https://so.toutiao.com/search?keyword=美国一男子被捕后几脚踢破墙越狱","word":"美国一男子被捕后几脚踢破墙越狱"},{"url":"https://so.toutiao.com/search?keyword=河南路边一棵树被砍成了“熊样”","word":"河南路边一棵树被砍成了“熊样”"},{"url":"https://so.toutiao.com/search?keyword=媒体：麦琳引发的熏鸡事变全网分食","word":"媒体：麦琳引发的熏鸡事变全网分食"},{"url":"https://so.toutiao.com/search?keyword=球迷冲入赛场挑衅日本门将后被抬走","word":"球迷冲入赛场挑衅日本门将后被抬走"},{"url":"https://so.toutiao.com/search?keyword=国足进球功臣林良铭曾加盟皇马","word":"国足进球功臣林良铭曾加盟皇马"},{"url":"https://so.toutiao.com/search?keyword=小伙在小米交付中心向雷军直投简历","word":"小伙在小米交付中心向雷军直投简历"},{"url":"https://so.toutiao.com/search?keyword=晨鸣纸业：三季度经营亏损严重","word":"晨鸣纸业：三季度经营亏损严重"},{"url":"https://so.toutiao.com/search?keyword=台反对乱港分子判决？外交部回应","word":"台反对乱港分子判决？外交部回应"},{"url":"https://so.toutiao.com/search?keyword=小蜜蜂老师离职事件疑云重重","word":"小蜜蜂老师离职事件疑云重重"},{"url":"https://so.toutiao.com/search?keyword=国际空间站漏气威胁航天员安全","word":"国际空间站漏气威胁航天员安全"},{"url":"https://so.toutiao.com/search?keyword=特朗普提名新闻主播达菲为交通部长","word":"特朗普提名新闻主播达菲为交通部长"},{"url":"https://so.toutiao.com/search?keyword=普京批准新版核威慑国家基本政策","word":"普京批准新版核威慑国家基本政策"},{"url":"https://so.toutiao.com/search?keyword=泰海域发现无头“美人鱼”疑遭猎杀","word":"泰海域发现无头“美人鱼”疑遭猎杀"},{"url":"https://so.toutiao.com/search?keyword=女子家中下水道冒出猪大肠","word":"女子家中下水道冒出猪大肠"},{"url":"https://so.toutiao.com/search?keyword=84岁姥姥背着狗狗走路","word":"84岁姥姥背着狗狗走路"},{"url":"https://so.toutiao.com/search?keyword=北京取消普宅和非普标准","word":"北京取消普宅和非普标准"},{"url":"https://so.toutiao.com/search?keyword=社区干部瓜分捐赠香烟？纪委介入","word":"社区干部瓜分捐赠香烟？纪委介入"},{"url":"https://so.toutiao.com/search?keyword=被老虎追咬可以反击进行紧急避险吗","word":"被老虎追咬可以反击进行紧急避险吗"},{"url":"https://so.toutiao.com/search?keyword=李行亮大学好友发声","word":"李行亮大学好友发声"},{"url":"https://so.toutiao.com/search?keyword=45名反中乱港分子被判刑","word":"45名反中乱港分子被判刑"},{"url":"https://so.toutiao.com/search?keyword=猫头鹰家里来了只猫","word":"猫头鹰家里来了只猫"},{"url":"https://so.toutiao.com/search?keyword=俄军宣布在库尔斯克包围近千名乌军","word":"俄军宣布在库尔斯克包围近千名乌军"},{"url":"https://so.toutiao.com/search?keyword=媒体人热议国足：冲4大有希望","word":"媒体人热议国足：冲4大有希望"},{"url":"https://so.toutiao.com/search?keyword=伊朗核基地被炸毁为何不反击？","word":"伊朗核基地被炸毁为何不反击？"},{"url":"https://so.toutiao.com/search?keyword=肺癌筛查和肺结节的误区有哪些","word":"肺癌筛查和肺结节的误区有哪些"},{"url":"https://so.toutiao.com/search?keyword=俄军新型高爆航空炸弹轰炸乌军","word":"俄军新型高爆航空炸弹轰炸乌军"},{"url":"https://so.toutiao.com/search?keyword=欧盟欲强迫中企转让技术以换取补助","word":"欧盟欲强迫中企转让技术以换取补助"},{"url":"https://so.toutiao.com/search?keyword=官方通报良品铺子被举报事件","word":"官方通报良品铺子被举报事件"},{"url":"https://so.toutiao.com/search?keyword=江门中微子实验探测器主体即将建成","word":"江门中微子实验探测器主体即将建成"},{"url":"https://so.toutiao.com/search?keyword=五菱“神车”鼻祖你见过吗","word":"五菱“神车”鼻祖你见过吗"},{"url":"https://so.toutiao.com/search?keyword=拜登对乌武器松绑为特朗普清障？","word":"拜登对乌武器松绑为特朗普清障？"},{"url":"https://so.toutiao.com/search?keyword=乌军米24直升机用机炮击落俄无人机","word":"乌军米24直升机用机炮击落俄无人机"},{"url":"https://so.toutiao.com/search?keyword=九华山景区多只狗断脚瘸腿","word":"九华山景区多只狗断脚瘸腿"},{"url":"https://so.toutiao.com/search?keyword=拜登对乌松绑导弹限制有何影响","word":"拜登对乌松绑导弹限制有何影响"},{"url":"https://so.toutiao.com/search?keyword=中方呼吁尽快实现苏丹停火止战","word":"中方呼吁尽快实现苏丹停火止战"},{"url":"https://so.toutiao.com/search?keyword=45336名观众现场观看中日之战","word":"45336名观众现场观看中日之战"},{"url":"https://so.toutiao.com/search?keyword=女子频繁美甲手上长甲周纤维瘤","word":"女子频繁美甲手上长甲周纤维瘤"},{"url":"https://so.toutiao.com/search?keyword=河南监狱管理局原局长李随军被除党籍","word":"河南监狱管理局原局长李随军被除党籍"},{"url":"https://so.toutiao.com/search?keyword=俄士兵依靠树木躲避无人机仍被击中","word":"俄士兵依靠树木躲避无人机仍被击中"},{"url":"https://so.toutiao.com/search?keyword=俄军“龙卷风”火箭炮18发连射","word":"俄军“龙卷风”火箭炮18发连射"},{"url":"https://so.toutiao.com/search?keyword=金灿荣：美国搞关税战损人不利己","word":"金灿荣：美国搞关税战损人不利己"},{"url":"https://so.toutiao.com/search?keyword=海水灌入北海市区：天文大潮所致","word":"海水灌入北海市区：天文大潮所致"},{"url":"https://so.toutiao.com/search?keyword=俄军官汽车行驶中遭乌爆炸袭击死亡","word":"俄军官汽车行驶中遭乌爆炸袭击死亡"},{"url":"https://so.toutiao.com/search?keyword=A股为何一天内大跌大涨","word":"A股为何一天内大跌大涨"},{"url":"https://so.toutiao.com/search?keyword=大叔站在拖拉机上用脚打方向盘倒车","word":"大叔站在拖拉机上用脚打方向盘倒车"},{"url":"https://so.toutiao.com/search?keyword=检察官将就是否撤销特朗普案提建议","word":"检察官将就是否撤销特朗普案提建议"},{"url":"https://so.toutiao.com/search?keyword=越野跑第二名因光膀子被取消成绩","word":"越野跑第二名因光膀子被取消成绩"},{"url":"https://so.toutiao.com/search?keyword=小学生看足球1年记录国足对战细节","word":"小学生看足球1年记录国足对战细节"},{"url":"https://so.toutiao.com/search?keyword=廖凡演活“不死不休”追谍英雄","word":"廖凡演活“不死不休”追谍英雄"}]