[{"query":"2023 答案奇遇夜","display_query":"2023 答案奇遇夜","url":"https://www.zhihu.com/search?q=2023%20答案奇遇夜"},{"query":"加利福尼亚州进入灾难状态","display_query":"加利福尼亚州进入灾难状态","url":"https://www.zhihu.com/search?q=加利福尼亚州进入灾难状态"},{"query":"尼泊尔一架载有 72 人的飞机坠毁","display_query":"尼泊尔一架载有 72 人的飞机坠毁","url":"https://www.zhihu.com/search?q=尼泊尔一架载有%2072%20人的飞机坠毁"},{"query":"中国奇谭第四集","display_query":"中国奇谭第四集","url":"https://www.zhihu.com/search?q=中国奇谭第四集"},{"query":"电影频道评三体动画失利","display_query":"电影频道评三体动画失利","url":"https://www.zhihu.com/search?q=电影频道评三体动画失利"},{"query":"iG 冠军野辅复出首战告负","display_query":"iG 冠军野辅复出首战告负","url":"https://www.zhihu.com/search?q=iG%20冠军野辅复出首战告负"},{"query":"剧版三体开播","display_query":"剧版三体开播","url":"https://www.zhihu.com/search?q=剧版三体开播"},{"query":"辽宁化工厂爆炸致 2 死","display_query":"辽宁化工厂爆炸致 2 死","url":"https://www.zhihu.com/search?q=辽宁化工厂爆炸致%202%20死"}]